Workbook

Sheet Cómo usar · How to
A1: BIBLIOTECA DE SERMONES — WATV Media Cast (Español + English)
A3: QUÉ ES ESTO · WHAT THIS IS
A4: Sermones, sermones resumidos y la serie mensual «Palabras de este mes» (Monthly Sermon Series),
A5: en español e inglés. Se leyeron los subtítulos hablados de cada vídeo, así que se puede buscar por TEMA,
A6: no solo por el título: ira y enojo, paciencia, perdón, diezmo y ofrenda, hijos, pruebas, humildad…
A7: COBERTURA · COVERAGE: índice por temas en 1861 de 1875 vídeos (4,611,304 palabras de transcripción leídas). Incluye 55 vídeos de la serie mensual.
A8: Videos without a topic index still appear in the Catalog with the site's own tags and summary.
A10: Every sermon, summary sermon and the monthly sermon series, in Spanish and English. The spoken subtitles
A11: of each video were read, so you can search by SUBJECT, not just by title.
A13: HOJAS · SHEETS
A14: Catálogo / Catalog — todos los vídeos, uno por fila, con «Idioma» (ES/EN) y filtros en la fila 1.
A15: Temas / Topics — cada tema con los vídeos que lo tratan, ordenados por cuánto lo tratan.
... A30: • Fuente / Source: watvmedia.org — sitio oficial. Los enlaces abren el vídeo original.

Sheet Buscar · Search
A1: Palabra o tema a buscar / Keyword or subject: | B1: enojo
A3: Vídeos que coinciden / matching videos: | B3: =COUNTIF('Catálogo · Catalog'!A:A,"SÍ")
A5: 1. Escribe tu palabra en la celda amarilla (B1). / Type your keyword in the yellow cell (B1).
A6: 2. Ve a «Catálogo» y filtra la columna «✅» = SÍ. / Go to «Catálogo» and filter «✅» = SÍ.
A7: 3.
A8: Busca sin acentos: «perdon», «ira», «diezmo», «hijos» / «anger», «tithe», «patience».
A9: Si la columna ✅ aparece vacía, pulsa F9 / If ✅ is blank, press F9.

Sheet Catálogo · Catalog
A1: ✅ | B1: Nº | C1: Idioma | D1: Tipo | E1: Título / Title | F1: Sección / Section | G1: Categoría / Category | H1: Canal / Channel | I1: Temas detectados / Topics | J1: Etiquetas / Tags | K1: Palabras frecuentes | L1: Duración | M1: Fecha | N1: Vistas | O1: Resumen / Summary | P1: Enlace / Link | Q1: YouTube
A2: =IF('Buscar · Search'!$B$1="","",IF(ISNUMBER(SEARCH('Buscar · Search'!$B$1,$E2&" "&$F2&" "&$G2&" "&$H2&" "&$I2&" "&$J2&" "&$K2&" "&$O2)),"SÍ","")) | B2: 1 | C2: ES | D2: Mensual | E2: Deben nacer de nuevo para entrar en el Reino de los Cielos | G2: Palabras de este mes | H2: Mother | I2: Amor y amor fraternal (20); Cielo, infierno y alma (9); Educación de los hijos y familia (8); Salvación y vida eterna (4); Evangelización y predicación (3); Avaricia y materialismo (3); Arrepentimiento (3) | K2: amor, cielo | L2: 05:24 | M2: 14 dic 2023 | N2: 14.331 | O2: Así como los hijos se parecen a sus padres,los hijos de Dios deben convertirse enamor pues Dios es amor.Él murió en lugar de Sus hijos queestaban destinados a entrar en elinfierno eterno debido a su p... | P2: https://watvmedia.org/es/media/be-born-again | Q2: https://youtu.be/5RniY9vQTW8
A3: =IF('Buscar · Search'!$B$1="","",IF(ISNUMBER(SEARCH('Buscar · Search'!$B$1,$E3&" "&$F3&" "&$G3&" "&$H3&" "&$I3&" "&$J3&" "&$K3&" "&$O3)),"SÍ","")) | B3: 2 | C3: ES | D3: Mensual | E3: Nuestra patria es el cielo: somos extranjeros sobre la tierra | G3: Palabras de este mes | H3: Mother | I3: Cielo, infierno y alma (10); Salvación y vida eterna (7); Educación de los hijos y familia (7); Arrepentimiento (6); Padre celestial (Cristo Ahnsahnghong) (5); Avaricia y materialismo (5); Familia celestial y Sion (3); Enfermedad y sanidad (3) | K3: cielo, reino, tierra, cielos, musica, mundo, patria | L3: 06:49 | M3: 5 mar 2025 | N3: 8.808 | O3: La razón por la que sufrimos el calor y el frío y padecemos mucho dolor, pena y amargura es porque somos extranjeros en esta tierra; este no es nuestro hogar.Dios se apiadó de la humanidad. Para lleva... | P3: https://watvmedia.org/es/media/our-home-is-heaven-we-are-strangers-in-this-world | Q3: https://youtu.be/xB3G2tj59lo
A4: =IF('Buscar · Search'!$B$1="","",IF(ISNUMBER(SEARCH('Buscar · Search'!$B$1,$E4&" "&$F4&" "&$G4&" "&$H4&" "&$I4&" "&$J4&" "&$K4&" "&$O4)),"SÍ","")) | B4: 3 | C4: ES | D4: Mensual | E4: El lino fino de Dios | G4: Palabras de este mes | H4: Mother | I4: Amor y amor fraternal (14); Salvación y vida eterna (13); Avaricia y materialismo (6); Palabras y lengua (hablar bien) (5); Pascua (4); La Biblia y su autoridad (3); Ira y enojo (control del temperamento) (3); Educación de los hijos y familia (3) | K4: amor, musica, reino, cielos, mundo | L4: 08:02 | M4: 30 abr 2025 | N4: 8.032 | O4: La Biblia, la palabra de Dios, es un libro que educa a la humanidad y muestra el camino de la salvación. Dios dice que, si llegamos a ser uno en amor, habremos cumplido la ley y nos explica que cuando... | P4: https://watvmedia.org/es/media/gods-linen | Q4: https://youtu.be/oZIkjRfwzJ0
A5: =IF('Buscar · Search'!$B$1="","",IF(ISNUMBER(SEARCH('Buscar · Search'!$B$1,$E5&" "&$F5&" "&$G5&" "&$H5&" "&$I5&" "&$J5&" "&$K5&" "&$O5)),"SÍ","")) | B5: 4 | C5: ES | D5: Mensual | E5: Una fe que practica la unidad | G5: Palabras de este mes | H5: Mother | I5: Cielo, infierno y alma (10); Unidad y armonía (6); Salvación y vida eterna (4); Perdón y reconciliación (4); Pruebas y tribulación (3); Evangelización y predicación (3); Enfermedad y sanidad (3) | K5: cielo, naturaleza | L5: 07:10 | M5: 18 oct 2024 | N5: 6.934 | O5: Ya que los seres humanos vinimos a esta tierra cometiendo graves pecados en el cielo, nuestros pecados no se limpian sin dolor. Además, siguen muchos dolores y sufrimientos en el proceso de nacer de n... | P5: https://watvmedia.org/es/media/united-faith | Q5: https://youtu.be/apILzd6Tk4w
A6: =IF('Buscar · Search'!$B$1="","",IF(ISNUMBER(SEARCH('Buscar · Search'!$B$1,$E6&" "&$F6&" "&$G6&" "&$H6&" "&$I6&" "&$J6&" "&$K6&" "&$O6)),"SÍ","")) | B6: 5 | C6: ES | D6: Mensual | E6: Edifiquemos a los demás con palabras amables y hermosas | G6: Palabras de este mes | H6: Mother | I6: Palabras y lengua (hablar bien) (22); Salvación y vida eterna (7); Educación de los hijos y familia (5); Ira y enojo (control del temperamento) (4); Fe y confianza en Dios (4); Alegría y felicidad (4); Humildad y orgullo (3) | K6: musica, sola | L6: 07:34 | M6: 17 jun 2025 | N6: 6.223 | O6: Las palabras son muy importantes en nuestra familia, en el mundo y en nuestra vida de la fe. En el libro de Génesis, Satanás condujo a Adán y Eva a la muerte con solo una palabra, y el ladrón que fue ... | P6: https://watvmedia.org/es/media/let-us-bestow-grace-with-good-and-beautiful-words | Q6: https://youtu.be/fkZ6-vsKyWk
A7: =IF('Buscar · Search'!$B$1="","",IF(ISNUMBER(SEARCH('Buscar · Search'!$B$1,$E7&" "&$F7&" "&$G7&" "&$H7&" "&$I7&" "&$J7&" "&$K7&" "&$O7)),"SÍ","")) | B7: 6 | C7: ES | D7: Mensual | E7: ¿Haciendo qué cosa heredaré la vida eterna? | G7: Palabras de este mes | H7: Mother | I7: Amor y amor fraternal (40); Cielo, infierno y alma (13); Salvación y vida eterna (8); Padre celestial (Cristo Ahnsahnghong) (6); Evangelización y predicación (5); Pascua (4); Palabras y lengua (hablar bien) (4) | K7: amor, misericordia, eterna, cielo, musica | L7: 06:53 | M7: 22 oct 2024 | N7: 6.007 | O7: Cuando alguien preguntó: “¿Haciendo qué cosa heredaré la vida eterna?”,Jesús le respondió utilizando la parábola del buen samaritano.Él enseñó que es importante guardar los mandamientos de Dios,pero a... | P7: https://watvmedia.org/es/media/how-eternal-life | Q7: https://youtu.be/CCXnn3rH3Ac
A8: =IF('Buscar · Search'!$B$1="","",IF(ISNUMBER(SEARCH('Buscar · Search'!$B$1,$E8&" "&$F8&" "&$G8&" "&$H8&" "&$I8&" "&$J8&" "&$K8&" "&$O8)),"SÍ","")) | B8: 7 | C8: ES | D8: Mensual | E8: Las cosas buenas y las cosas malas | G8: Palabras de este mes | H8: Mother | I8: Cielo, infierno y alma (11); Educación de los hijos y familia (8); Perdón y reconciliación (6); Palabras y lengua (hablar bien) (6); Amor y amor fraternal (6); Arrepentimiento (4); Salvación y vida eterna (3) | K8: buenas, cielo, musica | L8: 06:04 | M8: 24 ene 2025 | N8: 5.723 | O8: Al igual que en la parábola de pescar y separar los buenos peces de los malos, el reino de los cielos no es un lugar al que todos puedan acceder. Solo aquellos con una naturaleza amable, que considera... | P8: https://watvmedia.org/es/media/the-good-and-the-bad | Q8: https://youtu.be/F9SlsNoX-E0
A9: =IF('Buscar · Search'!$B$1="","",IF(ISNUMBER(SEARCH('Buscar · Search'!$B$1,$E9&" "&$F9&" "&$G9&" "&$H9&" "&$I9&" "&$J9&" "&$K9&" "&$O9)),"SÍ","")) | B9: 8 | C9: ES | D9: Mensual | E9: Conformarse a las sanas palabras y a la doctrina que es conforme a la piedad | G9: Palabras de este mes | H9: Mother | I9: Educación de los hijos y familia (8); Cielo, infierno y alma (5); Salvación y vida eterna (4); La Biblia y su autoridad (4); Palabras y lengua (hablar bien) (3); Amor y amor fraternal (3) | K9: piedad, musica, cielo, doctrina, conforme, reino | L9: 07:05 | M9: 22 nov 2024 | N9: 5.455 | O9: Ya que el pueblo del reino de los cielos son los hijos e hijas del Poderoso Creador Dios Ahnsahnghong, siempre debemos llevar una vida piadosa como hijos de Dios y dedicarnos a la palabra de Dios. “Co... | P9: https://watvmedia.org/es/media/focus-on-reverence-and-the-word | Q9: https://youtu.be/x9s09WQ8vgU
A10: =IF('Buscar · Search'!$B$1="","",IF(ISNUMBER(SEARCH('Buscar · Search'!$B$1,$E10&" "&$F10&" "&$G10&" "&$H10&" "&$I10&" "&$J10&" "&$K10&" "&$O10)),"SÍ","")) | B10: 9 | C10: ES | D10: Mensual | E10: Todas las naciones correrán a Sion por el camino de la vida | G10: Palabras de este mes | H10: Mother | I10: Salvación y vida eterna (16); Familia celestial y Sion (12); Pascua (11); Fiestas solemnes de Dios (5); La Biblia y su autoridad (4); Evangelización y predicación (4); El nuevo pacto (4) | K10: sion, pascua, eterna, salvacion, musica, fiesta, vino | L10: 06:58 | M10: 5 dic 2024 | N10: 5.328 | O10: La razón por la que Dios trae desastres en esta época es porque las personas abandonan su palabra.Jesús en su primera venida y Cristo Ahnsahnhong, Jesús que vino por segunda vez, trajeron la Pascua de... | P10: https://watvmedia.org/es/media/all-nations-find-their-way-to-zion | Q10: https://youtu.be/9tuU9dat83A
A11: =IF('Buscar · Search'!$B$1="","",IF(ISNUMBER(SEARCH('Buscar · Search'!$B$1,$E11&" "&$F11&" "&$G11&" "&$H11&" "&$I11&" "&$J11&" "&$K11&" "&$O11)),"SÍ","")) | B11: 10 | C11: ES | D11: Mensual | E11: Según las palabras de la profecía | G11: Palabras de este mes | H11: Mother | I11: Salvación y vida eterna (11); Cristo Ahnsahnghong y las profecías (9); La Biblia y su autoridad (8); Palabras y lengua (hablar bien) (7); Pascua (6); Cielo, infierno y alma (6); Arrepentimiento (4); Familia celestial y Sion (3) | K11: biblia, pascua, salvacion, camino, cielo, musica | L11: 06:23 | M11: 22 nov 2024 | N11: 5.270 | O11: Dios ha predestinado lo que sucederá incluso antes de la creación y ha estado llevando a cabo la obra de la redención según las profecías de la Biblia. Por lo tanto, debemos creer en las profecías.La ... | P11: https://watvmedia.org/es/media/words-of-prophecy | Q11: https://youtu.be/vZA_QFXcm0k
A12: =IF('Buscar · Search'!$B$1="","",IF(ISNUMBER(SEARCH('Buscar · Search'!$B$1,$E12&" "&$F12&" "&$G12&" "&$H12&" "&$I12&" "&$J12&" "&$K12&" "&$O12)),"SÍ","")) | B12: 11 | C12: ES | D12: Mensual | E12: Mirad, velad y orad | G12: Palabras de este mes | H12: Mother | I12: Salvación y vida eterna (10); Padre celestial (Cristo Ahnsahnghong) (4); Educación de los hijos y familia (4); Pascua (3); Cristo Ahnsahnghong y las profecías (3) | K12: nombre, salvos | L12: 05:51 | M12: 24 ene 2025 | N12: 5.128 | O12: La Iglesia de Dios, donde se celebra la verdad de la Pascua que nos protege del desastre, es Sion.Dios ha proporcionado refugio en cada época: el arca a Noé, Zoar a Lot, y Pella durante la destrucción... | P12: https://watvmedia.org/es/media/be-careful-stay-awake | Q12: https://youtu.be/mN68TO7sOws
A13: =IF('Buscar · Search'!$B$1="","",IF(ISNUMBER(SEARCH('Buscar · Search'!$B$1,$E13&" "&$F13&" "&$G13&" "&$H13&" "&$I13&" "&$J13&" "&$K13&" "&$O13)),"SÍ","")) | B13: 12 | C13: ES | D13: Mensual | E13: La mentalidad de un hijo y la mentalidad de un siervo | G13: Palabras de este mes | H13: Mother | I13: Educación de los hijos y familia (11); Salvación y vida eterna (7); Padre celestial (Cristo Ahnsahnghong) (7); Evangelización y predicación (5); Amor y amor fraternal (5); Cielo, infierno y alma (4); Enfermedad y sanidad (3) | K13: musica, celestial, reino, amor | L13: 06:50 | M13: 10 feb 2025 | N13: 4.857 | O13: Si somos hijos de Abraham, nuestra fe debe ser tan firme como la de Abraham,y si somos hijos de Dios, debemos salvar a las almas afligidas con amor, tal como Dios lo hizo.El sacerdocio real celestial ... | P13: https://watvmedia.org/es/media/the-spirit-of-a-son-and-the-spirit-of-a-servant | Q13: https://youtu.be/X_RsRokRoiI
... A28: =IF('Buscar · Search'!$B$1="","",IF(ISNUMBER(SEARCH('Buscar · Search'!$B$1,$E28&" "&$F28&" "&$G28&" "&$H28&" "&$I28&" "&$J28&" "&$K28&" "&$O28)),"SÍ","")) | B28: 27 | C28: ES | D28: Mensual | E28: La felicidad de los ciudadanos celestiales | G28: Palabras de este mes | H28: Mother | I28: Educación de los hijos y familia (10); Amor y amor fraternal (7); Salvación y vida eterna (6); Alegría y felicidad (6); Cielo, infierno y alma (5); Padre celestial (Cristo Ahnsahnghong) (4); Evangelización y predicación (4); Espíritu Santo y la Esposa (4) | K28: musica, reino, cielos, amor | L28: 07:15 | M28: 17 sept 2026 | N28: 361 | O28: Las personas que viven en esta tierra llevan una vida fatigosa, tengan mucho o poco. Al guardar la Pascua del nuevo pacto, nos hemos convertido en un cuerpo y una familia con Dios. Ya que Dios se ha c... | P28: https://watvmedia.org/es/media/heavenly-citizens-happiness | Q28: https://youtu.be/5rBt_xoVDxU
A29: =IF('Buscar · Search'!$B$1="","",IF(ISNUMBER(SEARCH('Buscar · Search'!$B$1,$E29&" "&$F29&" "&$G29&" "&$H29&" "&$I29&" "&$J29&" "&$K29&" "&$O29)),"SÍ","")) | B29: 28 | C29: ES | D29: Sermón | E29: Moisés, Jesús y la cruz | F29: Sermón | G29: Verdad | I29: La Biblia y su autoridad (63); Salvación y vida eterna (26); Cristo Ahnsahnghong y las profecías (20); Palabras y lengua (hablar bien) (11); Educación de los hijos y familia (11); Cielo, infierno y alma (10); Fe y confianza en Dios (9); Avaricia y materialismo (8) | J29: La cruz | K29: cruz, moises, serpiente, jesus, bronce, esto, jehova, israelitas, manos, biblia, discipulos, cuerda | L29: 43:04 | M29: 3 mar 2020 | N29: 260.398 | O29: Dios nos mostró la verdadera identidad de la cruz a través de MoisésMoisés fue una figura profética de la realidad de Jesús. Los israelitas ganaron la batalla de Refidimporque Moisés levantó sus manos... | P29: https://watvmedia.org/es/media/moses-jesus-and-the-cross | Q29: https://youtu.be/cxwcPg8IMw0
A30: =IF('Buscar · Search'!$B$1="","",IF(ISNUMBER(SEARCH('Buscar · Search'!$B$1,$E30&" "&$F30&" "&$G30&" "&$H30&" "&$I30&" "&$J30&" "&$K30&" "&$O30)),"SÍ","")) | B30: 29 | C30: ES | D30: Sermón | E30: Superemos la tentación y obtengamos el reino de los cielos | F30: Sermón | G30: Fe, Carácter | I30: La Biblia y su autoridad (40); Fe y confianza en Dios (40); Pruebas y tribulación (34); Educación de los hijos y familia (28); Cielo, infierno y alma (24); Avaricia y materialismo (16); Salvación y vida eterna (10); Dinero, trabajo y provisión (10) | J30: Fe, Resistencia | K30: satanas, tentacion, jehova, jesus, tierra, esto, cada, mundo, tentaciones, prueba, cielo, pruebas | L30: 44:00 | M30: 17 abr 2020 | N30: 245.181 | O30: Ya que Dios concede a sus hijos las bendiciones del cieloa través de cada culto, el acto de creer en Diosy adorarlo es en sí mismo alegría y felicidad.Los miembros de la Iglesia de Dios que vencen tod... | P30: https://watvmedia.org/es/media/lets-overcome-temptation-and-gain-the-kingdom-of-heaven | Q30: https://youtu.be/tnGd9GBR4t0
A31: =IF('Buscar · Search'!$B$1="","",IF(ISNUMBER(SEARCH('Buscar · Search'!$B$1,$E31&" "&$F31&" "&$G31&" "&$H31&" "&$I31&" "&$J31&" "&$K31&" "&$O31)),"SÍ","")) | B31: 30 | C31: ES | D31: Sermón | E31: La Madre Jerusalén | F31: Sermón | G31: Padre/Madre | I31: La Biblia y su autoridad (60); Educación de los hijos y familia (43); Amor y palabra de Dios Madre (31); Padre celestial (Cristo Ahnsahnghong) (29); Espíritu Santo y la Esposa (21); Palabras y lengua (hablar bien) (15); Salvación y vida eterna (10); La creación y el diseño de Dios (9) | J31: Madre, Dios Elohim | K31: esposa, creo, futuro, biblia, esto, voluntad, veamos, jesus, conocer, escrito, imagen, tierra | L31: 33:40 | M31: 13 abr 2018 | N31: 200.651 | O31: Todas las cosas de este mundo fueron creadas por la voluntad de Dios.Dios creó a todos los seres vivos para que recibieran vidaa través de sus madres. Esta es la gran voluntad de Diospara dar a conoce... | P31: https://watvmedia.org/es/media/jerusalem-mother | Q31: https://youtu.be/XtcsTw2J4oM
A32: =IF('Buscar · Search'!$B$1="","",IF(ISNUMBER(SEARCH('Buscar · Search'!$B$1,$E32&" "&$F32&" "&$G32&" "&$H32&" "&$I32&" "&$J32&" "&$K32&" "&$O32)),"SÍ","")) | B32: 31 | C32: ES | D32: Sermón | E32: Las profecías de los profetas y los pensamientos de la gente del mundo | F32: Sermón | G32: Padre/Madre, Verdad | I32: Cristo Ahnsahnghong y las profecías (70); La Biblia y su autoridad (52); Educación de los hijos y familia (23); Avaricia y materialismo (22); Padre celestial (Cristo Ahnsahnghong) (12); Evangelización y predicación (12); Salvación y vida eterna (9); Familia celestial y Sion (9) | J32: Dios en la carme, Salvación | K32: jesus, profecias, profetas, tierra, epoca, mundo, biblia, pensamientos, vino, hombre, diciendo, camino | L32: 36:55 | M32: 6 nov 2017 | N32: 184.021 | O32: Jesús nació como un niño según la profecía de la Biblia y entró en Jerusalén cabalgando un pollino.Sin embargo, los judíos no podían creer en Él, que vino a la tierra ocultando su naturaleza divina.Po... | P32: https://watvmedia.org/es/media/the-prophecies-of-prophets-the-thoughts-of-people-of-the-world | Q32: https://youtu.be/GTqj5lu2o6Q
A33: =IF('Buscar · Search'!$B$1="","",IF(ISNUMBER(SEARCH('Buscar · Search'!$B$1,$E33&" "&$F33&" "&$G33&" "&$H33&" "&$I33&" "&$J33&" "&$K33&" "&$O33)),"SÍ","")) | B33: 32 | C33: ES | D33: Sermón | E33: Dios Todopoderoso y el mundo de la fe | F33: Sermón | G33: Carácter | I33: Fe y confianza en Dios (76); La Biblia y su autoridad (27); Evangelización y predicación (18); Educación de los hijos y familia (18); Palabras y lengua (hablar bien) (14); Dinero, trabajo y provisión (10); Familia celestial y Sion (9); Cielo, infierno y alma (8) | J33: Resistencia, Humildad | K33: todopoderoso, tierra, aunque, tener, siempre, tiempo, camino, tesoro, omnipotente, poder, tenemos, obra | L33: 41:59 | M33: 3 dic 2018 | N33: 180.114 | O33: La fe después de comprender a Dios correctamente y la obra de DiosCuando solo consideramos nuestra situación, no podemos crecer en la fe sino que llegamos a quejarnos y murmurar. Cuando Gedeón, Job, N... | P33: https://watvmedia.org/es/media/almighty-god-the-world-of-faith | Q33: https://youtu.be/D4ZslvRzYMk
A34: =IF('Buscar · Search'!$B$1="","",IF(ISNUMBER(SEARCH('Buscar · Search'!$B$1,$E34&" "&$F34&" "&$G34&" "&$H34&" "&$I34&" "&$J34&" "&$K34&" "&$O34)),"SÍ","")) | B34: 33 | C34: ES | D34: Sermón | E34: La verdad y la falsedad | F34: Sermón | G34: El nuevo pacto y las fiestas, Verdad | I34: La Biblia y su autoridad (56); Pascua (28); Día de Reposo (sábado) (24); Cristo Ahnsahnghong y las profecías (23); Asistencia al culto y adoración (20); Cielo, infierno y alma (17); Salvación y vida eterna (15); Fe y confianza en Dios (15) | J34: Nuevo pacto, Mandamientos, Discernimiento de la falsedad | K34: jesus, cizana, pascua, reposo, apostoles, sembro, leyes, cielo, trigo, culto, cabeza, cielos | L34: 38:55 | M34: 21 nov 2019 | N34: 172.421 | O34: Hay incontables denominaciones y religiones en este mundo.Cada una de ellas insiste en que su creencia es verdadera.Sin embargo, Jesús distinguió la verdad de la falsedad mediante la parábola de la ci... | P34: https://watvmedia.org/es/media/truth-and-falsehood | Q34: https://youtu.be/_6x2BTVmSnQ
A35: =IF('Buscar · Search'!$B$1="","",IF(ISNUMBER(SEARCH('Buscar · Search'!$B$1,$E35&" "&$F35&" "&$G35&" "&$H35&" "&$I35&" "&$J35&" "&$K35&" "&$O35)),"SÍ","")) | B35: 34 | C35: ES | D35: Sermón | E35: El Salvador y el nombre nuevo | F35: Sermón | G35: Padre/Madre | I35: La Biblia y su autoridad (58); Espíritu Santo y la Esposa (37); Salvación y vida eterna (34); Educación de los hijos y familia (30); Padre celestial (Cristo Ahnsahnghong) (23); Oración (18); Fe y confianza en Dios (14); Cielo, infierno y alma (11) | J35: Padre, Dios en la carme | K35: nombre, jesus, epoca, jehova, espiritu, santo, salvacion, tiempo, biblia, salvador, orar, tiene | L35: 37:03 | M35: 16 jul 2018 | N35: 140.823 | O35: Dios da salvación en el nombre del Padre,del Hijo y del Espíritu SantoAsí como Dios dio diferentes mandamientos sobre la comida en cada época,dio diferentes nombres del Salvadoren la época del Padre, ... | P35: https://watvmedia.org/es/media/the-savior-the-new-name | Q35: https://youtu.be/A05MfufGejo
A36: =IF('Buscar · Search'!$B$1="","",IF(ISNUMBER(SEARCH('Buscar · Search'!$B$1,$E36&" "&$F36&" "&$G36&" "&$H36&" "&$I36&" "&$J36&" "&$K36&" "&$O36)),"SÍ","")) | B36: 35 | C36: ES | D36: Sermón | E36: La parábola de la higuera y Cristo Ahnsahnghong | F36: Sermón | I36: La Biblia y su autoridad (46); Cristo Ahnsahnghong y las profecías (35); Evangelización y predicación (16); Padre celestial (Cristo Ahnsahnghong) (11); Educación de los hijos y familia (7); Salvación y vida eterna (6); El nuevo pacto (6); Amor y palabra de Dios Madre (5) | J36: Padre | K36: higuera, jesus, profecia, parabola, hojas, higos, rama, tierna, israel, tierra, fruto, tiempo | L36: 29:55 | M36: 15 feb 2021 | N36: 123.219 | O36: ¿Quién inició la obra del evangelio en 1948 según la parábola de la higuera?Jesús les dijo a sus discípulos que aprendieran la parábola de la higuera, para hacernos saber el momento exacto en que vend... | P36: https://watvmedia.org/es/media/the-parable-of-the-fig-tree--christ-ahnsahnghong | Q36: https://youtu.be/hLnqYMAdrIk
A37: =IF('Buscar · Search'!$B$1="","",IF(ISNUMBER(SEARCH('Buscar · Search'!$B$1,$E37&" "&$F37&" "&$G37&" "&$H37&" "&$I37&" "&$J37&" "&$K37&" "&$O37)),"SÍ","")) | B37: 36 | C37: ES | D37: Sermón | E37: El que cree y el que no cree | F37: Sermón | G37: Fe, Verdad | I37: La Biblia y su autoridad (55); Educación de los hijos y familia (23); Cristo Ahnsahnghong y las profecías (17); Salvación y vida eterna (12); Padre celestial (Cristo Ahnsahnghong) (12); Palabras y lengua (hablar bien) (9); Espíritu Santo y la Esposa (9); Arrepentimiento (9) | J37: Salvación, Fe | K37: jesus, tierra, vino, biblia, carne, isaias, ojos, creer, apariencia, hombre, veamos, escribieron | L37: 38:12 | M37: 27 dic 2018 | N37: 123.033 | O37: Los miembros de la Iglesia de Dios han recibido a Dios que vino en la carne como lo hizo PedroDios da gracia a los que creen en Él, pero se convierte en un obstáculo para los que dudan o no creen. Nos... | P37: https://watvmedia.org/es/media/he-who-believes-he-who-doesnt | Q37: https://youtu.be/qbSmCxZq1h8
A38: =IF('Buscar · Search'!$B$1="","",IF(ISNUMBER(SEARCH('Buscar · Search'!$B$1,$E38&" "&$F38&" "&$G38&" "&$H38&" "&$I38&" "&$J38&" "&$K38&" "&$O38)),"SÍ","")) | B38: 37 | C38: ES | D38: Sermón | E38: El secreto del perdón de pecados y la Pascua | F38: Sermón | G38: El nuevo pacto y las fiestas | I38: Arrepentimiento (75); La Biblia y su autoridad (64); Cielo, infierno y alma (44); Pascua (32); Salvación y vida eterna (22); Perdón y reconciliación (21); Avaricia y materialismo (9); Familia celestial y Sion (8) | J38: Pascua | K38: tierra, pecados, cielo, pascua, jesus, biblia, vino, muerte, antes, perdon, cuerpo, embargo | L38: 35:13 | M38: 11 mar 2021 | N38: 121.936 | O38: ¿Quién perdona nuestros pecados mediante la Pascua del nuevo pacto?Para salvar a la humanidad que vino a la tierra por cometer en el reino de los cielos pecados que merecen la muerte, Dios mismo vino ... | P38: https://watvmedia.org/es/media/the-secret-of-the-forgiveness-of-sins-the-passover | Q38: https://youtu.be/2uGlLC6qDAE
A39: =IF('Buscar · Search'!$B$1="","",IF(ISNUMBER(SEARCH('Buscar · Search'!$B$1,$E39&" "&$F39&" "&$G39&" "&$H39&" "&$I39&" "&$J39&" "&$K39&" "&$O39)),"SÍ","")) | B39: 38 | C39: ES | D39: Sermón | E39: Prueba | F39: Sermón | G39: Fe | I39: Pruebas y tribulación (39); La Biblia y su autoridad (39); Fe y confianza en Dios (26); Salvación y vida eterna (21); Amor y palabra de Dios Madre (21); Avaricia y materialismo (15); Educación de los hijos y familia (12); Palabras y lengua (hablar bien) (8) | J39: Superando una prueba | K39: prueba, jesus, tierra, vino, conocer, creer, mundo, cielos, pregunta, dificil, eterna, reino | L39: 38:06 | M39: 24 sept 2019 | N39: 118.448 | O39: La fe sincera es la que no vacila en tiempos de dificultades y pruebasA través de la historia de los israelitas que murmuraron y se quejaron contra Dios durante su viaje de cuarenta años en el desiert... | P39: https://watvmedia.org/es/media/test | Q39: https://youtu.be/OvfqC9owxfI
A40: =IF('Buscar · Search'!$B$1="","",IF(ISNUMBER(SEARCH('Buscar · Search'!$B$1,$E40&" "&$F40&" "&$G40&" "&$H40&" "&$I40&" "&$J40&" "&$K40&" "&$O40)),"SÍ","")) | B40: 39 | C40: ES | D40: Sermón | E40: El Padre Ahnsahnghong es Dios, Cristo que vino por segunda vez II | F40: Sermón | G40: Padre/Madre | I40: La Biblia y su autoridad (68); Cristo Ahnsahnghong y las profecías (30); Evangelización y predicación (28); Padre celestial (Cristo Ahnsahnghong) (19); Educación de los hijos y familia (19); Bautismo (19); Juicio y segunda venida (16); El nuevo pacto (9) | J40: Padre, Dios en la carme | K40: jesus, david, tierra, segunda, biblia, venida, escrito, israel, evangelio, higuera, despues, pacto | L40: 36:10 | M40: 22 oct 2021 | N40: 117.483 | O40: Respecto a la pregunta: “El Señor Ahnsahnghong es un hombre. ¿Cómo puede ser Dios?”Cristo Ahnsahnghong es Dios porque solo Él es la raíz de David que vino en los últimos días y restauró el pacto etern... | P40: https://watvmedia.org/es/media/father-ahnsahnghong-is-god-christ-who-came-a-second-time-ii | Q40: https://youtu.be/HkdkaXYmtwg
A41: =IF('Buscar · Search'!$B$1="","",IF(ISNUMBER(SEARCH('Buscar · Search'!$B$1,$E41&" "&$F41&" "&$G41&" "&$H41&" "&$I41&" "&$J41&" "&$K41&" "&$O41)),"SÍ","")) | B41: 40 | C41: ES | D41: Sermón | E41: La Pascua y el Orden de Melquisedec | F41: Sermón | G41: El nuevo pacto y las fiestas | I41: Pascua (39); La Biblia y su autoridad (39); Salvación y vida eterna (27); El nuevo pacto (21); Servicio y sacrificio (18); Arrepentimiento (15); Perdón y reconciliación (12); Cena del Señor / Santa Cena (12) | J41: Nuevo pacto, Pascua | K41: melquisedec, orden, pacto, pascua, sangre, vino, traves, esto, jesus, sacerdote, sacerdocio, sacrificio | L41: 28:34 | M41: 23 nov 2017 | N41: 117.217 | O41: ¿Qué tipo de culto complace a Dios como el sacrificio de Abel?El orden de Melquisedec a través de la Pascua del nuevo pactoes el sacrificio invariable que Dios mismo estableció en la tierrapara que no... | P41: https://watvmedia.org/es/media/the-passover-the-order-of-melchizedek | Q41: https://youtu.be/DqVDdA60LgM
A42: =IF('Buscar · Search'!$B$1="","",IF(ISNUMBER(SEARCH('Buscar · Search'!$B$1,$E42&" "&$F42&" "&$G42&" "&$H42&" "&$I42&" "&$J42&" "&$K42&" "&$O42)),"SÍ","")) | B42: 41 | C42: ES | D42: Sermón | E42: ¿Por qué los hombres no pueden recordar el mundo anterior? | F42: Sermón | G42: Verdad | I42: Avaricia y materialismo (26); Padre celestial (Cristo Ahnsahnghong) (17); La Biblia y su autoridad (17); Cielo, infierno y alma (16); Salvación y vida eterna (15); Educación de los hijos y familia (15); Arrepentimiento (13); Amor y palabra de Dios Madre (7) | J42: Profecía | K42: mundo, reino, tierra, celestial, espiritu, principes, cielos, nobles, princesas, satanas, carne, anterior | L42: 23:26 | M42: 23 ene 2018 | N42: 112.214 | O42: Cristo Ahnsahnghong escribió en su libro Los Visitantes del Mundo Angelical, que los seres humanos eran nobles ángeles del cielo, pero cometieron pecadosy fueron arrojados a esta tierra, completamente... | P42: https://watvmedia.org/es/media/why-does-man-not-remember-his-previous-life | Q42: https://youtu.be/8wLIqAgnjgs
A43: =IF('Buscar · Search'!$B$1="","",IF(ISNUMBER(SEARCH('Buscar · Search'!$B$1,$E43&" "&$F43&" "&$G43&" "&$H43&" "&$I43&" "&$J43&" "&$K43&" "&$O43)),"SÍ","")) | B43: 42 | C43: ES | D43: Sermón | E43: Búscame | F43: Sermón | G43: Padre/Madre | I43: La Biblia y su autoridad (57); Padre celestial (Cristo Ahnsahnghong) (49); Amor y palabra de Dios Madre (45); Educación de los hijos y familia (32); Salvación y vida eterna (19); Cristo Ahnsahnghong y las profecías (19); Cielo, infierno y alma (11); Espíritu Santo y la Esposa (10) | J43: Madre, Dios en la carme | K43: pensamientos, biblia, espiritu, jesus, buscar, esposa, veamos, hombre, embargo, somos, tenemos, tener | L43: 32:40 | M43: 23 ene 2018 | N43: 108.735 | O43: Cuando los 300 guerreros de Gedeón derrotaron a 135 000 madianitas,el ejército de Gedeón ganó una victoria gracias a la obra de Dios.Del mismo modo, hay una gran diferenciaentre los pensamientos de Di... | P43: https://watvmedia.org/es/media/seek-me | Q43: https://youtu.be/-pbiFTBl-bo
A44: =IF('Buscar · Search'!$B$1="","",IF(ISNUMBER(SEARCH('Buscar · Search'!$B$1,$E44&" "&$F44&" "&$G44&" "&$H44&" "&$I44&" "&$J44&" "&$K44&" "&$O44)),"SÍ","")) | B44: 43 | C44: ES | D44: Sermón | E44: Dios, la fuente de la sabiduría | F44: Sermón | G44: Padre/Madre, El nuevo pacto y las fiestas, Verdad | I44: La Biblia y su autoridad (67); Salvación y vida eterna (35); Avaricia y materialismo (15); Fiestas solemnes de Dios (14); Familia celestial y Sion (14); Pascua (11); Amor y palabra de Dios Madre (10); Padre celestial (Cristo Ahnsahnghong) (9) | J44: Madre, Dios Elohim, Nuevo pacto, Pascua, Sion, Salvación | K44: sabiduria, biblia, salvacion, carne, habitacion, encontrar, conocimiento, mundo, tierra, sion, jesus, eterna | L44: 38:39 | M44: 26 nov 2019 | N44: 107.899 | O44: Mediante la historia de un rey que quería encontrar un siervo sabio, y la sabiduría de Zhuge Liang, podemos ver que la sabiduría es algo provechoso que nos permite superar las dificultades de la vida.... | P44: https://watvmedia.org/es/media/god-the-source-of-wisdom | Q44: https://youtu.be/vKl9sIzgwG0
A45: =IF('Buscar · Search'!$B$1="","",IF(ISNUMBER(SEARCH('Buscar · Search'!$B$1,$E45&" "&$F45&" "&$G45&" "&$H45&" "&$I45&" "&$J45&" "&$K45&" "&$O45)),"SÍ","")) | B45: 44 | C45: ES | D45: Sermón | E45: La Madre Jerusalén y la vida eterna | F45: Sermón | G45: Padre/Madre | I45: La Biblia y su autoridad (68); Salvación y vida eterna (51); Amor y palabra de Dios Madre (39); Educación de los hijos y familia (31); La creación y el diseño de Dios (15); Cielo, infierno y alma (13); Fe y confianza en Dios (10); Avaricia y materialismo (8) | J45: Madre | K45: eterna, biblia, madres, traves, tiene, creo, imagen, voluntad, postrero, esposa, tener, jesus | L45: 38:23 | M45: 30 oct 2018 | N45: 107.836 | O45: Todas las cosas creadas por Dios son como un libro que nos enseña el mundo espiritualDios creó a Eva (vida) en el sexto día de su obra de la creación, y dejó que todos los seres recibieran vida de sus... | P45: https://watvmedia.org/es/media/jerusalem-mother-eternal-life | Q45: https://youtu.be/0VeLCei_piM
A46: =IF('Buscar · Search'!$B$1="","",IF(ISNUMBER(SEARCH('Buscar · Search'!$B$1,$E46&" "&$F46&" "&$G46&" "&$H46&" "&$I46&" "&$J46&" "&$K46&" "&$O46)),"SÍ","")) | B46: 45 | C46: ES | D46: Sermón | E46: Una vida valiosa | F46: Sermón | G46: Fe | I46: Educación de los hijos y familia (30); La Biblia y su autoridad (23); Cielo, infierno y alma (20); Fe y confianza en Dios (18); Avaricia y materialismo (10); El nuevo pacto (9); Salvación y vida eterna (8); Padre celestial (Cristo Ahnsahnghong) (6) | J46: Predicación | K46: tierra, valiosa, cielo, siempre, testigos, padres, mundo, vivir, entender, eterno, pacto, reino | L46: 34:41 | M46: 16 ene 2020 | N46: 105.602 | O46: Las piedras que tenían valor antes de la civilización, no tienen valor en las sociedades modernas.Del mismo modo, hay una gran diferencia de valorentre las cosas terrenales y las cosas celestiales. Se... | P46: https://watvmedia.org/es/media/valuable-life | Q46: https://youtu.be/ah62NGEEoa4
A47: =IF('Buscar · Search'!$B$1="","",IF(ISNUMBER(SEARCH('Buscar · Search'!$B$1,$E47&" "&$F47&" "&$G47&" "&$H47&" "&$I47&" "&$J47&" "&$K47&" "&$O47)),"SÍ","")) | B47: 46 | C47: ES | D47: Sermón | E47: La Biblia Verdadera | F47: Sermón | G47: Verdad | I47: La Biblia y su autoridad (87); Palabras y lengua (hablar bien) (29); Cristo Ahnsahnghong y las profecías (26); Salvación y vida eterna (10); Asistencia al culto y adoración (10); Cielo, infierno y alma (9); Avaricia y materialismo (9); Arrepentimiento (5) | J47: Biblia | K47: biblia, tierra, siro, esto, imperio, agua, ciencia, persia, daniel, israelitas, despues, jehova | L47: 37:30 | M47: 23 nov 2017 | N47: 104.994 | O47: Dios Padre y Dios Madre guían cada época y la historiaA través de los registros bíblicos que preceden a la cienciay la historia del mundo que se desarrollaron de acuerdo con la palabra de Dios,podemos... | P47: https://watvmedia.org/es/media/the-true-bible | Q47: https://youtu.be/iZVtTHLO-qc
A48: =IF('Buscar · Search'!$B$1="","",IF(ISNUMBER(SEARCH('Buscar · Search'!$B$1,$E48&" "&$F48&" "&$G48&" "&$H48&" "&$I48&" "&$J48&" "&$K48&" "&$O48)),"SÍ","")) | B48: 47 | C48: ES | D48: Sermón | E48: Si conocen, amarán | F48: Sermón | G48: Padre/Madre, Fe | I48: La Biblia y su autoridad (52); Padre celestial (Cristo Ahnsahnghong) (34); Educación de los hijos y familia (34); Amor y palabra de Dios Madre (27); Evangelización y predicación (13); Cielo, infierno y alma (12); Avaricia y materialismo (9); Amor y amor fraternal (9) | J48: Dios Elohim, Predicación | K48: conocer, jesus, hormigas, biblia, pablo, jerusalen, conocemos, despues, tierra, antes, escrito, hormiga | L48: 39:42 | M48: 27 may 2019 | N48: 101.209 | O48: Cuanto más aprende sobre Dios, más llega a amarloPodemos llegar a amar a Dios cuando aprendemos correctamente sobre Él, al igual que el entomólogo que llegó a amar a las hormigas que había odiado ante... | P48: https://watvmedia.org/es/media/if-you-know-you-will-love | Q48: https://youtu.be/APvRsKIPbQQ
... A97: =IF('Buscar · Search'!$B$1="","",IF(ISNUMBER(SEARCH('Buscar · Search'!$B$1,$E97&" "&$F97&" "&$G97&" "&$H97&" "&$I97&" "&$J97&" "&$K97&" "&$O97)),"SÍ","")) | B97: 96 | C97: ES | D97: Sermón | E97: Vayamos al glorioso reino de Dios | F97: Sermón | G97: Fe, Verdad | I97: La Biblia y su autoridad (76); Humildad y orgullo (48); Dinero, trabajo y provisión (28); Cielo, infierno y alma (27); Salvación y vida eterna (22); Avaricia y materialismo (21); Pruebas y tribulación (12); Educación de los hijos y familia (7) | J97: Alma, Esperanza | K97: vanidad, tierra, cielo, esto, reino, mundo, hombre, cielos, trabajo, vayamos, despues, manos | L97: 34:29 | M97: 25 ene 2021 | N97: 64.274 | O97: La confesión de Salomón:“Todo debajo del sol es vanidad”.Dios nos ha enseñado mediante Salomón que todaslas cosas debajo del sol se desvanecen en un instante;son vanidad, y aflicción de espíritu.Para ... | P97: https://watvmedia.org/es/media/let-us-go-toward-the-glorious-kingdom-of-god | Q97: https://youtu.be/HWSgGdyfwr0
A98: =IF('Buscar · Search'!$B$1="","",IF(ISNUMBER(SEARCH('Buscar · Search'!$B$1,$E98&" "&$F98&" "&$G98&" "&$H98&" "&$I98&" "&$J98&" "&$K98&" "&$O98)),"SÍ","")) | B98: 97 | C98: ES | D98: Sermón | E98: La Madre Celestial Jerusalén | F98: Sermón | G98: Padre/Madre | H98: Mother | I98: La Biblia y su autoridad (70); Amor y palabra de Dios Madre (63); Educación de los hijos y familia (57); Salvación y vida eterna (38); Avaricia y materialismo (21); Padre celestial (Cristo Ahnsahnghong) (16); Palabras y lengua (hablar bien) (14); La creación y el diseño de Dios (13) | J98: Madre, Dios Elohim | K98: celestial, eterna, creo, biblia, voluntad, promesa, mundo, esposa, cordero, tierra, jerusalen, existe | L98: 32:59 | M98: 17 may 2022 | N98: 64.082 | O98: ¿Cómo podemos convertirnos en “los hijos de la promesa” que han recibido la vida eterna de Dios?La razón de que las efímeras vivan solo un día, los perros quince años, y los humanos cien años es que h... | P98: https://watvmedia.org/es/media/heavenly-mother-jerusalem | Q98: https://youtu.be/2Ep2owiC4hA
A99: =IF('Buscar · Search'!$B$1="","",IF(ISNUMBER(SEARCH('Buscar · Search'!$B$1,$E99&" "&$F99&" "&$G99&" "&$H99&" "&$I99&" "&$J99&" "&$K99&" "&$O99)),"SÍ","")) | B99: 98 | C99: ES | D99: Sermón | E99: Acerca del alma (2) | F99: Sermón | G99: Fe, Verdad | I99: Cielo, infierno y alma (48); Avaricia y materialismo (44); La Biblia y su autoridad (42); Educación de los hijos y familia (19); Salvación y vida eterna (10); Padre celestial (Cristo Ahnsahnghong) (8); Esperanza y consuelo (8); Resurrección y transformación (6) | J99: Alma, Esperanza | K99: mundo, alma, tierra, cuerpo, jesus, espiritual, esto, existe, embargo, biblia, experimentado, creer | L99: 32:08 | M99: 10 abr 2020 | N99: 63.456 | O99: La humanidad pecó en el cielo y vino a esta tierraSi comprendemos el asunto del alma,podemos saber cuál es la razón de la creación de los cielos y la tierra y por qué estamos viviendo en la tierra, y ... | P99: https://watvmedia.org/es/media/about-the-soul2 | Q99: https://youtu.be/YJRR-_nQygI
A100: =IF('Buscar · Search'!$B$1="","",IF(ISNUMBER(SEARCH('Buscar · Search'!$B$1,$E100&" "&$F100&" "&$G100&" "&$H100&" "&$I100&" "&$J100&" "&$K100&" "&$O100)),"SÍ","")) | B100: 99 | C100: ES | D100: Sermón | E100: El corazón de los Padres celestiales | F100: Sermón | G100: Padre/Madre | I100: Educación de los hijos y familia (113); Amor y amor fraternal (21); Pruebas y tribulación (16); La Biblia y su autoridad (13); El nuevo pacto (13); Cielo, infierno y alma (10); Salvación y vida eterna (8); Amor y palabra de Dios Madre (8) | J100: Padre, Madre, Dios Elohim, Sacrificio de Dios | K100: padres, amor, celestiales, pacto, camino, tierra, campesino, familia, cielo, aunque, dificultades, esposa | L100: 24:45 | M100: 23 ene 2018 | N100: 63.401 | O100: Así como los israelitas atravesaron muchas dificultades, pruebas y trampas en el desierto hacia Canaán, nosotros también podríamos tener dificultades y pruebas en el desierto de la fe. Dios quiere dar... | P100: https://watvmedia.org/es/media/the-heart-of-heavenly-parents | Q100: https://youtu.be/E7f6Uvg9-Rk
A101: =IF('Buscar · Search'!$B$1="","",IF(ISNUMBER(SEARCH('Buscar · Search'!$B$1,$E101&" "&$F101&" "&$G101&" "&$H101&" "&$I101&" "&$J101&" "&$K101&" "&$O101)),"SÍ","")) | B101: 100 | C101: ES | D101: Sermón | E101: Los mandamientos de Dios y el camino de la salvación | F101: Sermón | G101: El nuevo pacto y las fiestas | I101: La Biblia y su autoridad (30); Cielo, infierno y alma (30); Padre celestial (Cristo Ahnsahnghong) (18); Dinero, trabajo y provisión (15); Día de Reposo (sábado) (14); Educación de los hijos y familia (13); El nuevo pacto (12); Salvación y vida eterna (11) | J101: Mandamientos | K101: leyes, tierra, estatutos, ordenanzas, pacto, mandamientos, reposo, cielo, infierno, jehova, esto, dinero | L101: 30:23 | M101: 18 dic 2020 | N101: 63.356 | O101: Guardar los mandamientos de Dios es el camino de la salvaciónSatanás primero destruyó el Día de Reposo, el mandamiento de Dios, que es el camino de la salvación.Después, cuando desaparecieron todas la... | P101: https://watvmedia.org/es/media/gods-commandments-and-the-way-of-salvation | Q101: https://youtu.be/VqHgjbFP_VA
A102: =IF('Buscar · Search'!$B$1="","",IF(ISNUMBER(SEARCH('Buscar · Search'!$B$1,$E102&" "&$F102&" "&$G102&" "&$H102&" "&$I102&" "&$J102&" "&$K102&" "&$O102)),"SÍ","")) | B102: 101 | C102: ES | D102: Sermón | E102: Las Escrituras dicen que es necesario que así se haga | F102: Sermón | G102: Fe | I102: La Biblia y su autoridad (95); Educación de los hijos y familia (73); Padre celestial (Cristo Ahnsahnghong) (45); Amor y palabra de Dios Madre (38); Pascua (31); Avaricia y materialismo (14); Palabras y lengua (hablar bien) (12); Cielo, infierno y alma (9) | J102: Fe | K102: biblia, pascua, esto, familia, sangre, jesus, tierra, celestial, existe, figura, hombre, hagamos | L102: 36:11 | M102: 23 nov 2017 | N102: 63.219 | O102: La Biblia testifica que Dios vino a salvar a la humanidad.Podemos reconocer a Dios, que vino a salvarnos, si vemos la Biblia sin añadir nuestros pensamientos.La Biblia da a conocer a Dios MadreMuchos ... | P102: https://watvmedia.org/es/media/the-scriptures-that-say-it-must-happen-in-this-way | Q102: https://youtu.be/AoMWqbTfjfA
A103: =IF('Buscar · Search'!$B$1="","",IF(ISNUMBER(SEARCH('Buscar · Search'!$B$1,$E103&" "&$F103&" "&$G103&" "&$H103&" "&$I103&" "&$J103&" "&$K103&" "&$O103)),"SÍ","")) | B103: 102 | C103: ES | D103: Sermón | E103: Vendrá en las nubes | F103: Sermón | G103: Padre/Madre | I103: La Biblia y su autoridad (69); Cristo Ahnsahnghong y las profecías (25); Educación de los hijos y familia (22); Cielo, infierno y alma (21); Salvación y vida eterna (7); Palabras y lengua (hablar bien) (7); Juicio y segunda venida (7); Fe y confianza en Dios (5) | J103: Padre, Dios en la carme | K103: nube, tierra, carne, nubes, vendra, jesus, venida, hombre, cielo, vino, primera, gloria | L103: 22:56 | M103: 8 mar 2022 | N103: 62.949 | O103: ¿Por qué dijo Daniel que Jesús vendría con las nubes del cielo?La razón por la que se profetizó la primera y la segunda venida de Jesús en una nube es que la carne cubre la luz de la naturaleza divina... | P103: https://watvmedia.org/es/media/he-will-come-in-a-cloud | Q103: https://youtu.be/CAMnDrXt5NE
A104: =IF('Buscar · Search'!$B$1="","",IF(ISNUMBER(SEARCH('Buscar · Search'!$B$1,$E104&" "&$F104&" "&$G104&" "&$H104&" "&$I104&" "&$J104&" "&$K104&" "&$O104)),"SÍ","")) | B104: 103 | C104: ES | D104: Sermón | E104: He aquí que te he dado | F104: Sermón | G104: Fe, Carácter | I104: La Biblia y su autoridad (34); Salvación y vida eterna (11); Fe y confianza en Dios (11); Evangelización y predicación (10); Palabras y lengua (hablar bien) (9); El nuevo pacto (9); Padre celestial (Cristo Ahnsahnghong) (8); Cielo, infierno y alma (8) | J104: Confiar en Dios, Gloria a Dios, Gratitud | K104: tierra, recibido, gracias, sabiduria, pacto, esto, salomon, lugar, eterna, juan, mandamiento, siempre | L104: 32:31 | M104: 20 ene 2021 | N104: 61.940 | O104: ¿Por qué la humanidad debe vivir con gratitud?Debemos darnos cuenta de que todas las cosas necesarias para sustentar nuestra vida,sabiduría, conocimiento y poder que consideramos propios,en realidad s... | P104: https://watvmedia.org/es/media/i-will-give-you | Q104: https://youtu.be/eYCBceUmZpo
A105: =IF('Buscar · Search'!$B$1="","",IF(ISNUMBER(SEARCH('Buscar · Search'!$B$1,$E105&" "&$F105&" "&$G105&" "&$H105&" "&$I105&" "&$J105&" "&$K105&" "&$O105)),"SÍ","")) | B105: 104 | C105: ES | D105: Sermón | E105: Los que entrarán en el reino de Dios | F105: Sermón | G105: Fe | I105: Educación de los hijos y familia (33); La Biblia y su autoridad (25); Salvación y vida eterna (21); Cielo, infierno y alma (14); Arrepentimiento (14); Familia celestial y Sion (12); Amor y palabra de Dios Madre (12); Padre celestial (Cristo Ahnsahnghong) (10) | J105: Esperanza | K105: reino, jesus, escribas, fariseos, cielo, justicia, mayor, siento, somos, veamos, cielos, frutos | L105: 25:00 | M105: 21 mar 2018 | N105: 61.936 | O105: Jesús dijo que los que nacen de nuevo entrarán en el reino de Dios. Nacer de nuevo significa vaciarse, perdonarse unos a otros, y unirse mutuamente.Dios enseñó que aquellos cuya justicia y verdad fuer... | P105: https://watvmedia.org/es/media/those-who-will-enter-the-kingdom-of-god | Q105: https://youtu.be/_SyREHlwpN8
A106: =IF('Buscar · Search'!$B$1="","",IF(ISNUMBER(SEARCH('Buscar · Search'!$B$1,$E106&" "&$F106&" "&$G106&" "&$H106&" "&$I106&" "&$J106&" "&$K106&" "&$O106)),"SÍ","")) | B106: 105 | C106: ES | D106: Sermón | E106: Vengan al Espíritu y la Esposa | F106: Sermón | G106: Padre/Madre | I106: La Biblia y su autoridad (59); Educación de los hijos y familia (54); Espíritu Santo y la Esposa (33); Padre celestial (Cristo Ahnsahnghong) (32); Salvación y vida eterna (31); Amor y palabra de Dios Madre (30); Palabras y lengua (hablar bien) (11); Arrepentimiento (11) | J106: Padre, Madre, Dios Elohim | K106: espiritu, esposa, salvacion, imagen, biblia, agua, libro, tierra, sangre, reposo, lugar, humanidad | L106: 29:37 | M106: 30 ene 2019 | N106: 61.745 | O106: Debemos seguir el ejemplo de Noé y Lot, que se salvaron poniendo en práctica la palabra de DiosLos miembros de la Iglesia de Dios guardan las fiestas del nuevo pacto, incluyendo el Día de Reposo, la P... | P106: https://watvmedia.org/es/media/come-to-the-spirit-and-the-bride | Q106: https://youtu.be/AFC2YpPDick
A107: =IF('Buscar · Search'!$B$1="","",IF(ISNUMBER(SEARCH('Buscar · Search'!$B$1,$E107&" "&$F107&" "&$G107&" "&$H107&" "&$I107&" "&$J107&" "&$K107&" "&$O107)),"SÍ","")) | B107: 106 | C107: ES | D107: Sermón | E107: El amor y la unidad | F107: Sermón | G107: Carácter | I107: Amor y amor fraternal (60); La Biblia y su autoridad (30); Evangelización y predicación (23); Familia celestial y Sion (13); Unidad y armonía (12); Fe y confianza en Dios (11); Padre celestial (Cristo Ahnsahnghong) (8); Amor y palabra de Dios Madre (8) | J107: Unidad, Amor | K107: amor, cuerpo, miembros, evangelio, hojas, arboles, unidad, millones, conocimiento, siete, voluntad, mundo | L107: 26:10 | M107: 23 nov 2017 | N107: 61.211 | O107: El amor es lo que la gente de este mundo necesita desesperadamente. Con frecuencia, ocurren crímenes en todo el mundoporque el amor se está enfriando.El amor enseñado por Cristo Ahnsahnghong y Dios Ma... | P107: https://watvmedia.org/es/media/love-unity | Q107: https://youtu.be/IxwijTf71t8
A108: =IF('Buscar · Search'!$B$1="","",IF(ISNUMBER(SEARCH('Buscar · Search'!$B$1,$E108&" "&$F108&" "&$G108&" "&$H108&" "&$I108&" "&$J108&" "&$K108&" "&$O108)),"SÍ","")) | B108: 107 | C108: ES | D108: Sermón | E108: El valor del cielo y el valor del mundo | F108: Sermón | G108: Fe, Carácter | I108: Cielo, infierno y alma (54); Avaricia y materialismo (51); La Biblia y su autoridad (17); Padre celestial (Cristo Ahnsahnghong) (16); Salvación y vida eterna (14); Palabras y lengua (hablar bien) (14); Educación de los hijos y familia (12); Amor y palabra de Dios Madre (12) | J108: Esperanza, Fe, Palabras y Comportamiento | K108: cielo, mundo, valor, tiempo, tierra, estoy, esto, eterno, siempre, celestial, mente, gracias | L108: 29:31 | M108: 1 oct 2021 | N108: 61.095 | O108: Podemos ver lo que una persona considera valioso según su manera de hablarEl 98 % de lo que decimos queda grabado en nuestro cerebro. Cuando se graba un comentario negativo en nuestro cerebro, se nece... | P108: https://watvmedia.org/es/media/the-value-of-heaven--the-value-of-the-world | Q108: https://youtu.be/suqthP0rRCk
A109: =IF('Buscar · Search'!$B$1="","",IF(ISNUMBER(SEARCH('Buscar · Search'!$B$1,$E109&" "&$F109&" "&$G109&" "&$H109&" "&$I109&" "&$J109&" "&$K109&" "&$O109)),"SÍ","")) | B109: 108 | C109: ES | D109: Sermón | E109: Buenas palabras y buenas obras | F109: Sermón | G109: Carácter | I109: La Biblia y su autoridad (36); Avaricia y materialismo (32); Palabras y lengua (hablar bien) (28); Evangelización y predicación (7); Cielo, infierno y alma (7); Servicio y sacrificio (6); Salvación y vida eterna (6); Familia celestial y Sion (6) | J109: Palabras y Comportamiento, Servicio | K109: buenas, mundo, obras, biblia, cabeza, cada, veamos, cola, voluntad, haciendo, santo, jesus | L109: 23:24 | M109: 23 ene 2018 | N109: 60.985 | O109: Así como el mar no se contamina gracias al 3 % de sal que contiene, los hijos de Dios también deben asumir el papel de la sal del mundo con buenas palabras y buenas obras, sin seguir este mundo pecami... | P109: https://watvmedia.org/es/media/good-words-good-deeds | Q109: https://youtu.be/_tpaxWS0JZ0
A110: =IF('Buscar · Search'!$B$1="","",IF(ISNUMBER(SEARCH('Buscar · Search'!$B$1,$E110&" "&$F110&" "&$G110&" "&$H110&" "&$I110&" "&$J110&" "&$K110&" "&$O110)),"SÍ","")) | B110: 109 | C110: ES | D110: Sermón | E110: El rey David y Cristo Ahnsahnghong | F110: Sermón | G110: Padre/Madre, El nuevo pacto y las fiestas, Verdad | I110: La Biblia y su autoridad (70); Cristo Ahnsahnghong y las profecías (25); Bautismo (24); Evangelización y predicación (23); Educación de los hijos y familia (16); Padre celestial (Cristo Ahnsahnghong) (12); Juicio y segunda venida (8); El nuevo pacto (8) | J110: Padre, Nuevo pacto, Salvación | K110: david, trono, tierra, jesus, vino, evangelio, profecia, pacto, bautizado, reino, venida, carne | L110: 31:49 | M110: 8 may 2020 | N110: 60.677 | O110: “Era David de treinta años cuando comenzó a reinar, y reinó cuarenta años” (2 S. 5:4)Jesús, que vino a esta tierra por primera vez según la profecía del trono de David, se bautizó a la edad de treinta... | P110: https://watvmedia.org/es/media/king-david-and-christ-ahnsahnghong | Q110: https://youtu.be/XDgTiJV6UNI
... A127: =IF('Buscar · Search'!$B$1="","",IF(ISNUMBER(SEARCH('Buscar · Search'!$B$1,$E127&" "&$F127&" "&$G127&" "&$H127&" "&$I127&" "&$J127&" "&$K127&" "&$O127)),"SÍ","")) | B127: 126 | C127: ES | D127: Sermón | E127: Dios, el Salvador de la vida | F127: Sermón | G127: Fe, Carácter | I127: La Biblia y su autoridad (25); Gratitud y acción de gracias (15); Salvación y vida eterna (13); Cielo, infierno y alma (13); Educación de los hijos y familia (10); Fe y confianza en Dios (9); Familia celestial y Sion (7); Amor y amor fraternal (6) | J127: Fruto, Predicación, Pasión, Obediencia | K127: gracia, perro, salvador, tierra, gracias, pueblo, duena, jehova, esto, estamos, israel, egipto | L127: 36:09 | M127: 23 nov 2018 | N127: 51.986 | O127: Dios, el Salvador de la vida Todas las personas nacidas en esta tierra están destinadas a sufrir el dolor de la muerte y el castigo del infierno debido a sus graves pecados cometidos en el reino de lo... | P127: https://watvmedia.org/es/media/god-the-savior-of-our-life | Q127: https://youtu.be/osPUi1CAgfM
A128: =IF('Buscar · Search'!$B$1="","",IF(ISNUMBER(SEARCH('Buscar · Search'!$B$1,$E128&" "&$F128&" "&$G128&" "&$H128&" "&$I128&" "&$J128&" "&$K128&" "&$O128)),"SÍ","")) | B128: 127 | C128: ES | D128: Sermón | E128: Madre, gracias, la amamos | F128: Sermón | G128: Padre/Madre, Fe, Carácter | I128: La Biblia y su autoridad (24); Amor y palabra de Dios Madre (16); Pruebas y tribulación (15); Arrepentimiento (14); Resurrección y transformación (13); Avaricia y materialismo (13); Cielo, infierno y alma (12); Salvación y vida eterna (10) | J128: Madre, Esperanza, Resistencia, Gratitud | K128: gracias, esto, oruga, alas, siempre, ella, mundo, cielos, cielo, tierra, muerte, volar | L128: 35:22 | M128: 9 dic 2022 | N128: 51.982 | P128: https://watvmedia.org/es/media/mother-thank-you-and-we-love-you | Q128: https://youtu.be/KMhkM-yL3fU
A129: =IF('Buscar · Search'!$B$1="","",IF(ISNUMBER(SEARCH('Buscar · Search'!$B$1,$E129&" "&$F129&" "&$G129&" "&$H129&" "&$I129&" "&$J129&" "&$K129&" "&$O129)),"SÍ","")) | B129: 128 | C129: ES | D129: Sermón | E129: Los que no conocen el valor no tienen derecho a poseerlo | F129: Sermón | G129: El nuevo pacto y las fiestas, Fe | I129: Salvación y vida eterna (46); La Biblia y su autoridad (33); El nuevo pacto (29); Cielo, infierno y alma (20); Evangelización y predicación (16); Obediencia (13); Fe y confianza en Dios (13); Avaricia y materialismo (12) | J129: Mandamientos, Fe | K129: valor, pacto, reino, cielos, conocen, campo, tesoro, esto, tierra, salvacion, escondido, mundo | L129: 33:52 | M129: 17 jun 2021 | N129: 50.798 | O129: El reino de los cielos es semejante a un tesoro escondido en un campoComo el hombre que hizo grandes esfuerzos para obtener el tesoro escondido en el campo, solo aquellos que reconocen el valor del re... | P129: https://watvmedia.org/es/media/those-who-do-not-know-the-value-are-not-entitled-to-ownership | Q129: https://youtu.be/TpDfDjuW4BU
A130: =IF('Buscar · Search'!$B$1="","",IF(ISNUMBER(SEARCH('Buscar · Search'!$B$1,$E130&" "&$F130&" "&$G130&" "&$H130&" "&$I130&" "&$J130&" "&$K130&" "&$O130)),"SÍ","")) | B130: 129 | C130: ES | D130: Sermón | E130: Sigan el arca del pacto | F130: Sermón | G130: Padre/Madre | I130: La Biblia y su autoridad (37); Palabras y lengua (hablar bien) (13); Salvación y vida eterna (12); Educación de los hijos y familia (10); Cielo, infierno y alma (8); Evangelización y predicación (7); Espíritu Santo y la Esposa (6); Padre celestial (Cristo Ahnsahnghong) (5) | J130: Padre, Madre, Dios Elohim | K130: arca, pacto, tierra, delante, columna, pueblo, josue, israelitas, camino, jehova, siempre, canaan | L130: 32:23 | M130: 12 ene 2019 | N130: 49.911 | O130: Quien muestre su justicia no podrá entrar en el reino de los cielosDios siempre hizo que el arca del pacto estuviera al frente y los israelitas lo siguieran, cuando los condujo por el desierto durante... | P130: https://watvmedia.org/es/media/follow-the-ark-of-the-covenant | Q130: https://youtu.be/Jn9-NVFEJEM
A131: =IF('Buscar · Search'!$B$1="","",IF(ISNUMBER(SEARCH('Buscar · Search'!$B$1,$E131&" "&$F131&" "&$G131&" "&$H131&" "&$I131&" "&$J131&" "&$K131&" "&$O131)),"SÍ","")) | B131: 130 | C131: ES | D131: Sermón | E131: La Pascua es la verdad que salva vidas | F131: Sermón | G131: El nuevo pacto y las fiestas, Verdad | I131: Pascua (71); La Biblia y su autoridad (52); Avaricia y materialismo (16); Palabras y lengua (hablar bien) (8); Educación de los hijos y familia (7); Salvación y vida eterna (5); El nuevo pacto (5); Evangelización y predicación (4) | J131: Pascua, Desastre | K131: pascua, tierra, jesus, veamos, sangre, esto, mundo, despues, senal, casas, desastres, egipto | L131: 33:48 | M131: 20 mar 2020 | N131: 49.884 | O131: Todas las personas nacidas en esta tierra, han de morir, y deben prepararse para la vida después de la muerte, según la palabra de Dios que vive para siempre.La Pascua del nuevo pacto que nos permite ... | P131: https://watvmedia.org/es/media/the-passover-is-the-truth-that-saves-life | Q131: https://youtu.be/yYJdU-NhvFM
A132: =IF('Buscar · Search'!$B$1="","",IF(ISNUMBER(SEARCH('Buscar · Search'!$B$1,$E132&" "&$F132&" "&$G132&" "&$H132&" "&$I132&" "&$J132&" "&$K132&" "&$O132)),"SÍ","")) | B132: 131 | C132: ES | D132: Sermón | E132: La tentación y la victoria | F132: Sermón | G132: Fe | I132: Pruebas y tribulación (46); La Biblia y su autoridad (31); Educación de los hijos y familia (22); Arrepentimiento (22); Fe y confianza en Dios (20); Oración (9); Cielo, infierno y alma (9); Padre celestial (Cristo Ahnsahnghong) (7) | J132: Confiar en Dios, Superando una prueba, Fe | K132: jesus, prueba, tentacion, satanas, pruebas, abraham, pecados, tentaciones, camino, veamos, escrito, cielo | L132: 30:01 | M132: 28 ene 2019 | N132: 49.812 | O132: Quien muestre su justicia no podrá entrar en el reino de los cielosDios siempre hizo que el arca del pacto estuviera delante de los israelitas cuando los condujo por el desierto durante cuarenta años ... | P132: https://watvmedia.org/es/media/temptation-victory | Q132: https://youtu.be/t-6vWuZOR6k
A133: =IF('Buscar · Search'!$B$1="","",IF(ISNUMBER(SEARCH('Buscar · Search'!$B$1,$E133&" "&$F133&" "&$G133&" "&$H133&" "&$I133&" "&$J133&" "&$K133&" "&$O133)),"SÍ","")) | B133: 132 | C133: ES | D133: Sermón | E133: ¿Qué es lo más valioso en el cielo? | F133: Sermón | G133: El nuevo pacto y las fiestas, Fe | I133: La Biblia y su autoridad (43); Cielo, infierno y alma (25); Salvación y vida eterna (9); Avaricia y materialismo (8); Palabras y lengua (hablar bien) (7); Obediencia (7); Fe y confianza en Dios (6); Ira y enojo (control del temperamento) (5) | J133: Nuevo pacto, Esperanza | K133: valioso, cielo, tierra, serpiente, valor, bronce, moises, nabucodonosor, jehova, biblia, siempre, estatua | L133: 29:28 | M133: 5 mar 2021 | N133: 49.732 | O133: ¿Dónde podemos encontrar la vida realmente valiosa que durará para siempre?A través de la Biblia, Dios nos enseñó a llevar una vida realmente valiosa que nos permita disfrutar de la gloria del cielo.C... | P133: https://watvmedia.org/es/media/what-has-the-greatest-value-in-heaven | Q133: https://youtu.be/4dNUT7YNuTc
A134: =IF('Buscar · Search'!$B$1="","",IF(ISNUMBER(SEARCH('Buscar · Search'!$B$1,$E134&" "&$F134&" "&$G134&" "&$H134&" "&$I134&" "&$J134&" "&$K134&" "&$O134)),"SÍ","")) | B134: 133 | C134: ES | D134: Sermón | E134: La Madre, la Fuente del Agua de la Vida | F134: Sermón | G134: Padre/Madre | I134: La Biblia y su autoridad (51); Educación de los hijos y familia (32); Espíritu Santo y la Esposa (28); Amor y palabra de Dios Madre (21); Cristo Ahnsahnghong y las profecías (20); Palabras y lengua (hablar bien) (18); Enfermedad y sanidad (12); Avaricia y materialismo (11) | J134: Madre, Dios en la carme, Dios Elohim | K134: agua, jerusalen, esposa, espiritu, aguas, biblia, apocalipsis, cordero, hacia, mundo, sale, naciones | L134: 25:17 | M134: 13 abr 2018 | N134: 49.339 | O134: Así como ninguna criatura viviente puede vivir sin agua,nuestra alma debe recibir el agua de la vida del Espíritu y la Esposa para tener vida.Y el Espíritu y la Esposa dicen: Ven. […] y el que quiera,... | P134: https://watvmedia.org/es/media/mother-the-source-of-the-water-of-life | Q134: https://youtu.be/qporbTDwy5E
A135: =IF('Buscar · Search'!$B$1="","",IF(ISNUMBER(SEARCH('Buscar · Search'!$B$1,$E135&" "&$F135&" "&$G135&" "&$H135&" "&$I135&" "&$J135&" "&$K135&" "&$O135)),"SÍ","")) | B135: 134 | C135: ES | D135: Sermón | E135: La Santa Comunión de la Pascua que Dios nos ordenó celebrar | F135: Sermón | G135: El nuevo pacto y las fiestas | I135: Pascua (116); La Biblia y su autoridad (66); Salvación y vida eterna (36); Educación de los hijos y familia (21); Cielo, infierno y alma (13); Padre celestial (Cristo Ahnsahnghong) (12); El nuevo pacto (12); Arrepentimiento (11) | J135: Pascua | K135: pascua, jesus, sangre, carne, esto, discipulos, pacto, vino, apostol, pablo, traves, comer | L135: 39:57 | M135: 6 abr 2020 | N135: 49.129 | O135: La Iglesia de Dios celebra la Pascua según el mandamiento de Dios.Jesús prometió dar vida eterna a aquellosque comen el pan y beben el vino de la Pascua.Si creemos en Jesús, debemos seguir sus enseñan... | P135: https://watvmedia.org/es/media/the-passover-holy-supper--god-commanded-us-to-keep | Q135: https://youtu.be/P3Nw98WzMM8
A136: =IF('Buscar · Search'!$B$1="","",IF(ISNUMBER(SEARCH('Buscar · Search'!$B$1,$E136&" "&$F136&" "&$G136&" "&$H136&" "&$I136&" "&$J136&" "&$K136&" "&$O136)),"SÍ","")) | B136: 135 | C136: ES | D136: Sermón | E136: ¿Qué haré ahora, Señor? | F136: Sermón | G136: Carácter | I136: La Biblia y su autoridad (21); Evangelización y predicación (21); Educación de los hijos y familia (19); Familia celestial y Sion (17); Padre celestial (Cristo Ahnsahnghong) (16); Salvación y vida eterna (11); Fe y confianza en Dios (11); Cielo, infierno y alma (10) | J136: Gratitud, Unidad | K136: obra, tiempo, hare, voluntad, camino, lugar, situacion, pablo, cielo, tierra, apostol, haga | L136: 32:46 | M136: 3 ago 2021 | N136: 48.906 | O136: ¿Cómo podemos recibir las bendiciones de Dios?Cuando enfrentamos dificultades en nuestra vida de la fe, no debemos quejarnos, pensando: ¿Por qué yo? sino que debemos darnos cuenta de la providencia de... | P136: https://watvmedia.org/es/media/lord-what-shall-i-do-now | Q136: https://youtu.be/8W77XaLS7Ps
A137: =IF('Buscar · Search'!$B$1="","",IF(ISNUMBER(SEARCH('Buscar · Search'!$B$1,$E137&" "&$F137&" "&$G137&" "&$H137&" "&$I137&" "&$J137&" "&$K137&" "&$O137)),"SÍ","")) | B137: 136 | C137: ES | D137: Sermón | E137: El poder de la palabra de Dios | F137: Sermón | G137: Padre/Madre | I137: Educación de los hijos y familia (25); La Biblia y su autoridad (24); Perdón y reconciliación (7); Fe y confianza en Dios (7); Arrepentimiento (7); Amor y palabra de Dios Madre (6); Palabras y lengua (hablar bien) (5); Espíritu Santo y la Esposa (5) | J137: Padre, Dios en la carme | K137: jesus, epoca, poder, vino, tierra, carne, esto, pecados, paso, hombre, dara, estaban | L137: 15:49 | M137: 7 dic 2018 | N137: 48.633 | O137: El poder de las palabras de Dios en la época del Espíritu Santo es mayor que en las épocas del Padre y del HijoAl ver los milagros mostrados en el nacimiento de Isaac y en las bodas de Caná, y los mil... | P137: https://watvmedia.org/es/media/the-power-of-gods-word | Q137: https://youtu.be/JGitdc0AuJI
A138: =IF('Buscar · Search'!$B$1="","",IF(ISNUMBER(SEARCH('Buscar · Search'!$B$1,$E138&" "&$F138&" "&$G138&" "&$H138&" "&$I138&" "&$J138&" "&$K138&" "&$O138)),"SÍ","")) | B138: 137 | C138: ES | D138: Sermón | E138: Ascender al cielo caminando con Dios | F138: Sermón | G138: Carácter | I138: La Biblia y su autoridad (47); Día de Reposo (sábado) (28); Pascua (27); Cielo, infierno y alma (23); Salvación y vida eterna (13); Evangelización y predicación (12); Avaricia y materialismo (10); Educación de los hijos y familia (7) | J138: Obediencia | K138: jesus, ejemplo, reposo, pascua, cielo, caminar, camino, seguir, caminando, iglesias, biblia, guardar | L138: 31:07 | M138: 25 mar 2020 | N138: 48.464 | O138: Seguir el ejemplo de Dioses la manera de caminar con DiosPara que caminemos con Dios y ascendamos al cieloal igual que los antepasados de la fe como Enoc, Noé y Abraham, debemos seguir el ejemplo que ... | P138: https://watvmedia.org/es/media/ascending-to-heaven-while-walking-with-god | Q138: https://youtu.be/4rg-AJ432q0
A139: =IF('Buscar · Search'!$B$1="","",IF(ISNUMBER(SEARCH('Buscar · Search'!$B$1,$E139&" "&$F139&" "&$G139&" "&$H139&" "&$I139&" "&$J139&" "&$K139&" "&$O139)),"SÍ","")) | B139: 138 | C139: ES | D139: Sermón | E139: Quien quiera llevar la corona, debe soportar su peso | F139: Sermón | G139: Fe, Carácter | I139: La Biblia y su autoridad (32); Evangelización y predicación (27); Cielo, infierno y alma (18); Salvación y vida eterna (13); Pruebas y tribulación (13); Avaricia y materialismo (12); El nuevo pacto (7); Educación de los hijos y familia (7) | J139: Superando una prueba, Obediencia | K139: cruz, camino, peso, soportar, corona, cielo, siglos, jesus, evangelio, mundo, siempre, cada | L139: 31:14 | M139: 23 abr 2020 | N139: 48.217 | O139: “Los que reinarán por los siglos de los siglos deben soportar el peso de la cruz”Dios dijo que si queremos reinar por los siglos de los siglosen el glorioso reino de los cielos,debemos tomar nuestra p... | P139: https://watvmedia.org/es/media/the-one-who-wants-to-wear-the-crown-must-bear-its-weight | Q139: https://youtu.be/P93mu1zKAck
A140: =IF('Buscar · Search'!$B$1="","",IF(ISNUMBER(SEARCH('Buscar · Search'!$B$1,$E140&" "&$F140&" "&$G140&" "&$H140&" "&$I140&" "&$J140&" "&$K140&" "&$O140)),"SÍ","")) | B140: 139 | C140: ES | D140: Sermón | E140: Somos bienaventurados | F140: Sermón | G140: Carácter | I140: Cielo, infierno y alma (57); La Biblia y su autoridad (27); Padre celestial (Cristo Ahnsahnghong) (21); Amor y palabra de Dios Madre (18); Evangelización y predicación (16); Salvación y vida eterna (13); Familia celestial y Sion (11); El nuevo pacto (8) | J140: Gratitud | K140: cielo, tierra, entrar, camino, reino, cielos, angeles, evangelio, pacto, esto, elecciones, nombre | L140: 31:30 | M140: 14 may 2021 | N140: 48.099 | O140: Si tuviéramos que entrar en el reino de los cielos a través de los votos de los ángeles,¿quiénes entrarían en el cielo?El reino de los cielos no es un lugar en donde uno pueda entrar por voto como el ... | P140: https://watvmedia.org/es/media/we-are-blessed | Q140: https://youtu.be/G6YP9lvGQ8I
... A165: =IF('Buscar · Search'!$B$1="","",IF(ISNUMBER(SEARCH('Buscar · Search'!$B$1,$E165&" "&$F165&" "&$G165&" "&$H165&" "&$I165&" "&$J165&" "&$K165&" "&$O165)),"SÍ","")) | B165: 164 | C165: ES | D165: Sermón | E165: Muestren la santidad de Dios | F165: Sermón | G165: Fe | I165: La Biblia y su autoridad (25); Cielo, infierno y alma (12); Educación de los hijos y familia (6); Palabras y lengua (hablar bien) (4); Fe y confianza en Dios (4); Humildad y orgullo (3); Enfermedad y sanidad (3); Asistencia al culto y adoración (3) | J165: Gloria a Dios | K165: moises, gloria, nabucodonosor, pueblo, aaron, delante, daniel, trono, poder, santidad, cielo, herodes | L165: 29:54 | M165: 22 ene 2021 | N165: 41.582 | O165: Solo Dios gobierna los cielos y la tierraMoisés y Aarón no pudieron entrar en la tierra de Canaán al final del viaje de cuarenta años por el desierto, y Nabucodonosor vivió como un animal salvaje dura... | P165: https://watvmedia.org/es/media/display-gods-holiness | Q165: https://youtu.be/jNXfMv2K2bU
A166: =IF('Buscar · Search'!$B$1="","",IF(ISNUMBER(SEARCH('Buscar · Search'!$B$1,$E166&" "&$F166&" "&$G166&" "&$H166&" "&$I166&" "&$J166&" "&$K166&" "&$O166)),"SÍ","")) | B166: 165 | C166: ES | D166: Sermón | E166: La voz de la Madre celestial | F166: Sermón | G166: Padre/Madre, Verdad | H166: Mother | I166: Amor y palabra de Dios Madre (75); Educación de los hijos y familia (61); La Biblia y su autoridad (40); Padre celestial (Cristo Ahnsahnghong) (39); Espíritu Santo y la Esposa (10); Alegría y felicidad (10); Evangelización y predicación (9); Amor y amor fraternal (8) | J166: Madre, Dios Elohim, Salvación | K166: celestial, madres, tierra, esto, padres, siempre, escuchar, ella, tiene, espiritu, amor, celestiales | L166: 32:52 | M166: 17 feb 2023 | N166: 41.251 | O166: Todo el mundo quiere oír más la voz de una madre; lo mismo sucede en el mundo espiritualAsí como las personas encuentran paz y consuelo a través de las voces de sus madres que escucharon en el vientre... | P166: https://watvmedia.org/es/media/heavenly-mothers-voice | Q166: https://youtu.be/2JzomcQYGBM
A167: =IF('Buscar · Search'!$B$1="","",IF(ISNUMBER(SEARCH('Buscar · Search'!$B$1,$E167&" "&$F167&" "&$G167&" "&$H167&" "&$I167&" "&$J167&" "&$K167&" "&$O167)),"SÍ","")) | B167: 166 | C167: ES | D167: Sermón | E167: La familia celestial y la familia terrenal III | F167: Sermón | G167: Padre/Madre | I167: Educación de los hijos y familia (157); La Biblia y su autoridad (36); Amor y palabra de Dios Madre (24); Amor y amor fraternal (23); Padre celestial (Cristo Ahnsahnghong) (22); Familia celestial y Sion (18); Honrar a los padres (12); Avaricia y materialismo (11) | J167: Madre, Dios Elohim | K167: padres, familia, amor, deber, filial, celestiales, biblia, ensenanzas, embargo, mundo, esto, jehova | L167: 35:48 | M167: 2 jul 2018 | N167: 40.480 | O167: Podemos entender a Dios Padre y a Dios Madrea través del sistema familiarDios nos permitió entender que en el cieloestá la familia celestial, que es la realidad,a través del sistema familiar terrenal,... | P167: https://watvmedia.org/es/media/heavenly-family-earthly-family-3 | Q167: https://youtu.be/OkLgZ9qKwdA
A168: =IF('Buscar · Search'!$B$1="","",IF(ISNUMBER(SEARCH('Buscar · Search'!$B$1,$E168&" "&$F168&" "&$G168&" "&$H168&" "&$I168&" "&$J168&" "&$K168&" "&$O168)),"SÍ","")) | B168: 167 | C168: ES | D168: Sermón | E168: Planes para el cielo y planes para la jubilación | F168: Sermón | G168: Fe, Verdad | I168: Cielo, infierno y alma (56); La Biblia y su autoridad (30); Salvación y vida eterna (21); Padre celestial (Cristo Ahnsahnghong) (16); Avaricia y materialismo (15); Fe y confianza en Dios (9); Evangelización y predicación (7); Amor y palabra de Dios Madre (7) | J168: Salvación, Predicación | K168: cielo, tierra, reino, cielos, rico, planes, hombre, mundo, lazaro, ultimos, muerte, infierno | L168: 33:12 | M168: 14 nov 2019 | N168: 40.363 | O168: Mucha gente en el mundo considera importantes los planes para sus últimos años, pero no se preparan para el mundo eterno que vendrá después de la muerte.Necesitamos hacer preparativos para ir al cielo... | P168: https://watvmedia.org/es/media/plans-for-heaven-and-plans-for-retirement | Q168: https://youtu.be/P6T4Y0gPWGA
A169: =IF('Buscar · Search'!$B$1="","",IF(ISNUMBER(SEARCH('Buscar · Search'!$B$1,$E169&" "&$F169&" "&$G169&" "&$H169&" "&$I169&" "&$J169&" "&$K169&" "&$O169)),"SÍ","")) | B169: 168 | C169: ES | D169: Sermón | E169: La Pascua es el camino y la verdad | F169: Sermón | G169: El nuevo pacto y las fiestas | I169: Pascua (57); La Biblia y su autoridad (35); Salvación y vida eterna (18); Cielo, infierno y alma (13); Avaricia y materialismo (13); El nuevo pacto (10); Amor y palabra de Dios Madre (10); Palabras y lengua (hablar bien) (7) | J169: Pascua | K169: pascua, jesus, camino, ejemplo, esto, pacto, mundo, tierra, biblia, traves, reino, cielos | L169: 28:37 | M169: 10 mar 2021 | N169: 40.121 | O169: ¿Cuál es el camino al cielo dado por Dios?La última cena es una obra de arte muy conocida en el mundo entero. Jesús deseó guardar ansiosamente la Pascua del nuevo pacto. Solo a través de esta verdad, ... | P169: https://watvmedia.org/es/media/the-passover-is-the-way-and-the-truth | Q169: https://youtu.be/kkWTlhZMvzM
A170: =IF('Buscar · Search'!$B$1="","",IF(ISNUMBER(SEARCH('Buscar · Search'!$B$1,$E170&" "&$F170&" "&$G170&" "&$H170&" "&$I170&" "&$J170&" "&$K170&" "&$O170)),"SÍ","")) | B170: 169 | C170: ES | D170: Sermón | E170: Los que pueden oír correctamente la voz de Dios | F170: Sermón | G170: Padre/Madre, El nuevo pacto y las fiestas | I170: La Biblia y su autoridad (57); Padre celestial (Cristo Ahnsahnghong) (24); Espíritu Santo y la Esposa (19); Educación de los hijos y familia (19); Amor y palabra de Dios Madre (18); Salvación y vida eterna (13); Cristo Ahnsahnghong y las profecías (11); La creación y el diseño de Dios (10) | J170: Padre, Madre, Dios Elohim, Nuevo pacto | K170: espiritu, biblia, ensenanzas, juan, esposa, claramente, tiene, correctamente, salvacion, pueblo, genesis, imagen | L170: 28:18 | M170: 30 oct 2020 | N170: 40.019 | O170: “Bienaventurados vuestros oídos porque oyen”En este mundo, hay dos grupos de personas:los que oyen y hacen lo que Dios dice, y los que no pueden entender,por más que escuchen la voz de Dios.En la époc... | P170: https://watvmedia.org/es/media/those-who-can-hear-the-voice-of-god | Q170: https://youtu.be/DJs4Mg4TZXs
A171: =IF('Buscar · Search'!$B$1="","",IF(ISNUMBER(SEARCH('Buscar · Search'!$B$1,$E171&" "&$F171&" "&$G171&" "&$H171&" "&$I171&" "&$J171&" "&$K171&" "&$O171)),"SÍ","")) | B171: 170 | C171: ES | D171: Sermón | E171: La Navidad, el día del nacimiento equivocado | F171: Sermón | G171: Verdad | I171: La Biblia y su autoridad (46); Salvación y vida eterna (9); Fe y confianza en Dios (9); Avaricia y materialismo (6); Cielo, infierno y alma (5); Pascua (4); Educación de los hijos y familia (4); Padre celestial (Cristo Ahnsahnghong) (3) | J171: Adoración al dios Sol | K171: navidad, nacimiento, jesus, biblia, mandamientos, diciembre, hombres, veamos, origen, romano, tiene, tener | L171: 24:01 | M171: 19 dic 2022 | N171: 39.900 | O171: ¿Cuál es la verdad de la Navidad que todo el mundo conoce como el día del nacimiento de Jesús?Las costumbres de las tres festividades principales de Roma: Saturnales, Sigilares y Brumales, y Santa Cla... | P171: https://watvmedia.org/es/media/christmas-the-made-up-birthday | Q171: https://youtu.be/KJXAGgI2uJA
A172: =IF('Buscar · Search'!$B$1="","",IF(ISNUMBER(SEARCH('Buscar · Search'!$B$1,$E172&" "&$F172&" "&$G172&" "&$H172&" "&$I172&" "&$J172&" "&$K172&" "&$O172)),"SÍ","")) | B172: 171 | C172: ES | D172: Sermón | E172: Los que confían en la palabra de Dios y los que no | F172: Sermón | G172: Fe | I172: La Biblia y su autoridad (39); Fe y confianza en Dios (19); Educación de los hijos y familia (19); Cielo, infierno y alma (14); Arrepentimiento (11); Evangelización y predicación (10); Amor y palabra de Dios Madre (10); Salvación y vida eterna (8) | J172: Confiar en Dios, Poder de Dios | K172: tierra, cielos, veamos, poder, cielo, camino, tiene, esto, israelitas, aquellos, jesus, aunque | L172: 31:32 | M172: 19 jul 2021 | N172: 39.721 | O172: Dios da bendiciones cuando lo seguimos, confiando en su palabra.Así como Dios bendijo a los padres de la fe como Abraham, Noé y Pedro cuando confiaron en la palabra de Dios, aún más en una situación d... | P172: https://watvmedia.org/es/media/those-who-rely-on-gods-word--those-who-do-not | Q172: https://youtu.be/aHB0BV9aYxs
A173: =IF('Buscar · Search'!$B$1="","",IF(ISNUMBER(SEARCH('Buscar · Search'!$B$1,$E173&" "&$F173&" "&$G173&" "&$H173&" "&$I173&" "&$J173&" "&$K173&" "&$O173)),"SÍ","")) | B173: 172 | C173: ES | D173: Sermón | E173: La obra de la salvación a través de la Madre | F173: Sermón | G173: Padre/Madre | H173: Mother | I173: La Biblia y su autoridad (63); Amor y palabra de Dios Madre (54); Educación de los hijos y familia (43); Espíritu Santo y la Esposa (16); La creación y el diseño de Dios (15); Enfermedad y sanidad (15); Salvación y vida eterna (14); Dinero, trabajo y provisión (11) | J173: Madre | K173: adan, traves, esposa, cordero, adam, espiritual, genesis, dolor, jerusalen, obra, biblia, cuerpo | L173: 29:55 | M173: 3 jun 2021 | N173: 39.713 | O173: La obra de salvación que llevan a cabo el Padre Ahnsahnghong y la Madre celestialLa obra final de la salvación será cumplida por el Padre Ahnsahnghong, quien restauró la verdad del nuevo pacto como el... | P173: https://watvmedia.org/es/media/the-work-of-salvation-through-mother | Q173: https://youtu.be/OPI_I6XlDak
A174: =IF('Buscar · Search'!$B$1="","",IF(ISNUMBER(SEARCH('Buscar · Search'!$B$1,$E174&" "&$F174&" "&$G174&" "&$H174&" "&$I174&" "&$J174&" "&$K174&" "&$O174)),"SÍ","")) | B174: 173 | C174: ES | D174: Sermón | E174: Las características del cristianismo auténtico y de la herejía | F174: Sermón | G174: El nuevo pacto y las fiestas, Verdad | I174: La Biblia y su autoridad (55); Pascua (27); Evangelización y predicación (16); Palabras y lengua (hablar bien) (9); Salvación y vida eterna (8); El nuevo pacto (8); Día de Reposo (sábado) (7); Avaricia y materialismo (7) | J174: Nuevo pacto, Herejía, Adoración al dios Sol, Discernimiento de la falsedad | K174: pedro, autentica, jesus, pascua, herejia, biblia, pablo, herejes, apostol, autenticidad, evangelio, esto | L174: 28:39 | M174: 3 sept 2020 | N174: 38.973 | O174: ¿La Iglesia de Dios tiene la verdad que guardaron Pedro y Pablo?La Iglesia de Dios, a la que asistieron Pedro y Pablo,fue establecida por Jesús y defiendelas enseñanzas auténticas desde la época apost... | P174: https://watvmedia.org/es/media/the-characteristics-of-authenticity-and-heresy | Q174: https://youtu.be/TzAtQ-UsBy0
A175: =IF('Buscar · Search'!$B$1="","",IF(ISNUMBER(SEARCH('Buscar · Search'!$B$1,$E175&" "&$F175&" "&$G175&" "&$H175&" "&$I175&" "&$J175&" "&$K175&" "&$O175)),"SÍ","")) | B175: 174 | C175: ES | D175: Sermón | E175: Un buen árbol lleva buenos frutos | F175: Sermón | G175: Padre/Madre, Fe | I175: Amor y palabra de Dios Madre (50); Paciencia y dominio propio (28); La Biblia y su autoridad (17); Evangelización y predicación (16); Avaricia y materialismo (10); Dinero, trabajo y provisión (8); Salvación y vida eterna (5); Palabras y lengua (hablar bien) (4) | J175: Madre, Confiar en Dios | K175: siempre, nunca, buenos, frutos, porter, mejor, paciencia, paciente, ensenanzas, aunque, rechazado, evangelio | L175: 28:47 | M175: 20 may 2021 | N175: 38.917 | O175: La Iglesia de Dios recibe nuevas fuerzas por el aliento de Dios MadreAunque Bill Porter nació con parálisis cerebral, se convirtió en el mejor vendedor gracias al aliento de su madre. De la misma mane... | P175: https://watvmedia.org/es/media/a-good-tree-bears-good-fruit | Q175: https://youtu.be/a2MOjkZLRik
A176: =IF('Buscar · Search'!$B$1="","",IF(ISNUMBER(SEARCH('Buscar · Search'!$B$1,$E176&" "&$F176&" "&$G176&" "&$H176&" "&$I176&" "&$J176&" "&$K176&" "&$O176)),"SÍ","")) | B176: 175 | C176: ES | D176: Sermón | E176: La comida dada por Dios | F176: Sermón | G176: El nuevo pacto y las fiestas | I176: Pascua (36); La Biblia y su autoridad (34); Cielo, infierno y alma (29); Educación de los hijos y familia (18); Salvación y vida eterna (15); Padre celestial (Cristo Ahnsahnghong) (8); El nuevo pacto (8); Palabras y lengua (hablar bien) (6) | J176: Nuevo pacto, Pascua | K176: comida, mana, pascua, cielo, jesus, dada, carne, sangre, desierto, vino, comer, descendio | L176: 29:56 | M176: 23 nov 2017 | N176: 38.001 | O176: En la sociedad moderna, mucha gente quiere estar saludable a través de la comida. Las personas llaman “comida dada por Dios” a los alimentos que ayudan en la prolongación de la vida. Sin embargo, la v... | P176: https://watvmedia.org/es/media/god-given-food | Q176: https://youtu.be/dAGa7ztkTWc
A177: =IF('Buscar · Search'!$B$1="","",IF(ISNUMBER(SEARCH('Buscar · Search'!$B$1,$E177&" "&$F177&" "&$G177&" "&$H177&" "&$I177&" "&$J177&" "&$K177&" "&$O177)),"SÍ","")) | B177: 176 | C177: ES | D177: Sermón | E177: Las características de los falsos profetas | F177: Sermón | G177: El nuevo pacto y las fiestas, Verdad | I177: Cristo Ahnsahnghong y las profecías (60); La Biblia y su autoridad (54); Día de Reposo (sábado) (15); Cielo, infierno y alma (14); Educación de los hijos y familia (12); Asistencia al culto y adoración (10); Palabras y lengua (hablar bien) (7); Salvación y vida eterna (6) | J177: Mandamientos, Discernimiento de la falsedad | K177: profetas, falsos, mandamientos, hombres, caracteristicas, jehova, guardan, reposo, biblia, escrito, pueblo, jesus | L177: 30:06 | M177: 2 nov 2021 | N177: 37.992 | O177: Los verdaderos profetas guardan y enseñan los mandamientos de Dios tales como el Día de Reposo y la PascuaEl culto dominical y la Navidad son para adorar al dios sol, y pertenecen a los mandamientos d... | P177: https://watvmedia.org/es/media/the-characteristics-of-false-prophets | Q177: https://youtu.be/sfxZQD36LQQ
A178: =IF('Buscar · Search'!$B$1="","",IF(ISNUMBER(SEARCH('Buscar · Search'!$B$1,$E178&" "&$F178&" "&$G178&" "&$H178&" "&$I178&" "&$J178&" "&$K178&" "&$O178)),"SÍ","")) | B178: 177 | C178: ES | D178: Sermón | E178: Los que se arrepienten y los que no se arrepienten | F178: Sermón | G178: El nuevo pacto y las fiestas, Fe | I178: Arrepentimiento (93); La Biblia y su autoridad (30); Evangelización y predicación (16); Oración (9); Cielo, infierno y alma (8); Salvación y vida eterna (7); Humildad y orgullo (6); Asistencia al culto y adoración (5) | J178: Fiesta de las Trompetas, Arrepentimiento, Predicación | K178: jonas, arrepentimiento, pablo, pecador, ninive, esto, camino, apostol, jesus, jehova, pecados, tierra | L178: 31:15 | M178: 19 dic 2022 | N178: 37.776 | O178: Cristo Ahnsahnghong y Dios Madre nos enseñaron el verdadero significado del arrepentimientoTodos los seres humanos somos pecadores que pecamos en el cielo y vinimos a esta tierra.Si entendemos que som... | P178: https://watvmedia.org/es/media/those-who-repent-those-who-dont-repent | Q178: https://youtu.be/5pKG-qav3TU
A179: =IF('Buscar · Search'!$B$1="","",IF(ISNUMBER(SEARCH('Buscar · Search'!$B$1,$E179&" "&$F179&" "&$G179&" "&$H179&" "&$I179&" "&$J179&" "&$K179&" "&$O179)),"SÍ","")) | B179: 178 | C179: ES | D179: Sermón | E179: La Madre celestial y el Lugar Santísimo | F179: Sermón | G179: Padre/Madre | I179: Arrepentimiento (52); La Biblia y su autoridad (37); Perdón y reconciliación (33); Amor y palabra de Dios Madre (25); Asistencia al culto y adoración (23); Padre celestial (Cristo Ahnsahnghong) (11); Palabras y lengua (hablar bien) (9); Cielo, infierno y alma (9) | J179: Madre | K179: lugar, santisimo, pecados, santuario, entrar, velo, templo, perdon, santo, jesus, celestial, entro | L179: 32:01 | M179: 11 mar 2021 | N179: 37.740 | O179: La Madre Celestial Nueva Jerusalén, el Lugar Santísimo donde los pecados son perdonadosCuando la humanidad vaya a la Madre Jerusalén Celestial, la realidad del Lugar Santísimo, todos los pecados volve... | P179: https://watvmedia.org/es/media/heavenly-mother-the-most-holy-place | Q179: https://youtu.be/ZULVrbvb174
A180: =IF('Buscar · Search'!$B$1="","",IF(ISNUMBER(SEARCH('Buscar · Search'!$B$1,$E180&" "&$F180&" "&$G180&" "&$H180&" "&$I180&" "&$J180&" "&$K180&" "&$O180)),"SÍ","")) | B180: 179 | C180: ES | D180: Sermón | E180: La salvación concedida a los que perseveren hasta el fin | F180: Sermón | G180: Fe, Carácter | I180: La Biblia y su autoridad (43); Fe y confianza en Dios (27); Salvación y vida eterna (24); Familia celestial y Sion (24); Educación de los hijos y familia (23); Padre celestial (Cristo Ahnsahnghong) (12); Cielo, infierno y alma (12); Paciencia y dominio propio (11) | J180: Fe, Resistencia | K180: sion, satanas, salvacion, sera, esposa, final, biblia, tierra, jehova, accion, esto, dinastia | L180: 32:54 | M180: 11 jun 2021 | N180: 37.701 | O180: Los miembros de la Iglesia de Dios están siempre con Dios en SionDurante la dinastía Zhou, la esposa de Jiang Taigong no pudo convertirse en reina porque no pudo soportar el sufrimiento hasta el final... | P180: https://watvmedia.org/es/media/salvation-granted-to-those-who-endure-until-the-end | Q180: https://youtu.be/hxZ71hTb-aQ
A181: =IF('Buscar · Search'!$B$1="","",IF(ISNUMBER(SEARCH('Buscar · Search'!$B$1,$E181&" "&$F181&" "&$G181&" "&$H181&" "&$I181&" "&$J181&" "&$K181&" "&$O181)),"SÍ","")) | B181: 180 | C181: ES | D181: Sermón | E181: La vida como el rocío sobre la hierba | F181: Sermón | G181: Fe, Verdad | I181: La Biblia y su autoridad (27); Cielo, infierno y alma (19); Salvación y vida eterna (17); Humildad y orgullo (15); Avaricia y materialismo (14); Arrepentimiento (10); Palabras y lengua (hablar bien) (9); Juicio y segunda venida (9) | J181: Salvación, Temor a Dios | K181: tierra, tiempo, despues, esto, vanidad, hombre, mundo, cielo, viento, lazaro, juicio, rico | L181: 30:23 | M181: 12 mar 2021 | N181: 37.304 | O181: La vida más valiosa es prepararse para las cosas eternasIncluso las personas que habían tenido una gran vida, como Salomón, Napoleón y Alejandro Magno, testificaron que nuestra vida en la tierra es va... | P181: https://watvmedia.org/es/media/life-like-the-dew-on-the-grass | Q181: https://youtu.be/5QBG60mXNxc
A182: =IF('Buscar · Search'!$B$1="","",IF(ISNUMBER(SEARCH('Buscar · Search'!$B$1,$E182&" "&$F182&" "&$G182&" "&$H182&" "&$I182&" "&$J182&" "&$K182&" "&$O182)),"SÍ","")) | B182: 181 | C182: ES | D182: Sermón | E182: La palabra de Dios y su poder | F182: Sermón | G182: Carácter | I182: La Biblia y su autoridad (38); Palabras y lengua (hablar bien) (24); Educación de los hijos y familia (23); Salvación y vida eterna (8); Padre celestial (Cristo Ahnsahnghong) (8); Espíritu Santo y la Esposa (7); Cristo Ahnsahnghong y las profecías (7); Amor y palabra de Dios Madre (6) | J182: Obediencia | K182: jehova, tierra, viva, jesus, camino, profeta, veamos, carne, josue, agua, espiritu, esto | L182: 33:13 | M182: 26 abr 2021 | N182: 36.836 | O182: La palabra de Dios también se cumple en esta épocaNosotros, la humanidad, debemos creer que la palabra de Dios ciertamente se cumple, lo cual podemos aprender de la historia de aquellos que siguieron ... | P182: https://watvmedia.org/es/media/word-of-god-and-its-power | Q182: https://youtu.be/7zA7MKRQzj8
A183: =IF('Buscar · Search'!$B$1="","",IF(ISNUMBER(SEARCH('Buscar · Search'!$B$1,$E183&" "&$F183&" "&$G183&" "&$H183&" "&$I183&" "&$J183&" "&$K183&" "&$O183)),"SÍ","")) | B183: 182 | C183: ES | D183: Sermón | E183: Sé celoso, porque el reino de los cielos se ha acercado | F183: Sermón | G183: Fe | I183: La Biblia y su autoridad (33); Cielo, infierno y alma (33); Salvación y vida eterna (19); Educación de los hijos y familia (17); Avaricia y materialismo (13); Padre celestial (Cristo Ahnsahnghong) (9); Palabras y lengua (hablar bien) (5); Fe y confianza en Dios (5) | J183: Fe | K183: cielo, isla, tierra, reino, cielos, hogar, vivir, mundo, cruzo, robinson, eterno, esto | L183: 29:56 | M183: 8 ene 2018 | N183: 36.597 | O183: Las bendiciones que Dios da a los que trabajan duro para el evangelio, comprendiendo el valor del reino de los cielosNo seamos como Esaú, que se arrepintió de haber perdido las bendiciones de Dios tra... | P183: https://watvmedia.org/es/media/be-earnest-for-the-kingdom-of-heaven-is-near | Q183: https://youtu.be/_LHPJQVVXqg
A184: =IF('Buscar · Search'!$B$1="","",IF(ISNUMBER(SEARCH('Buscar · Search'!$B$1,$E184&" "&$F184&" "&$G184&" "&$H184&" "&$I184&" "&$J184&" "&$K184&" "&$O184)),"SÍ","")) | B184: 183 | C184: ES | D184: Sermón | E184: El rey David y Cristo Ahnsahnghong (II) | F184: Sermón | G184: Padre/Madre, Verdad | I184: La Biblia y su autoridad (49); Cristo Ahnsahnghong y las profecías (43); Padre celestial (Cristo Ahnsahnghong) (15); Salvación y vida eterna (14); Evangelización y predicación (13); Educación de los hijos y familia (11); Cielo, infierno y alma (10); Palabras y lengua (hablar bien) (9) | J184: Padre, Dios en la carme, Profecía | K184: david, jesus, profecia, jehova, tierra, trono, vino, biblia, profecias, reino, pacto, esto | L184: 27:36 | M184: 8 oct 2020 | N184: 36.121 | O184: Dios nos advirtió que no menospreciemos las profecías de la BibliaPara que la humanidad reciba la gracia de la salvación, debemos creeren las profecías de la Biblia y acercarnos a Dios a través del cu... | P184: https://watvmedia.org/es/media/king-david-and-christ-ahnsahnghong-2 | Q184: https://youtu.be/leL77t59shA
A185: =IF('Buscar · Search'!$B$1="","",IF(ISNUMBER(SEARCH('Buscar · Search'!$B$1,$E185&" "&$F185&" "&$G185&" "&$H185&" "&$I185&" "&$J185&" "&$K185&" "&$O185)),"SÍ","")) | B185: 184 | C185: ES | D185: Sermón | E185: Dios puede hacerlo todo | F185: Sermón | G185: Fe | I185: Avaricia y materialismo (62); Fe y confianza en Dios (46); La Biblia y su autoridad (29); Evangelización y predicación (21); Cielo, infierno y alma (7); La creación y el diseño de Dios (6); Salvación y vida eterna (3); Palabras y lengua (hablar bien) (3) | J185: Fe, Predicación | K185: mundo, esto, tierra, evangelio, fisico, embargo, aunque, luna, samaria, ultimo, poder, gravedad | L185: 30:36 | M185: 12 ago 2022 | N185: 35.783 | O185: Cuando tenemos fe, se manifiesta el mundo de la fe que no se puede ver a simple vista.Dios gobierna el mundo de la fe, donde todo se cumple como Él lo planeó.Dios dividió el Mar Rojo con una vara, der... | P185: https://watvmedia.org/es/media/360 | Q185: https://youtu.be/EoCAD-SzDZs
... A248: =IF('Buscar · Search'!$B$1="","",IF(ISNUMBER(SEARCH('Buscar · Search'!$B$1,$E248&" "&$F248&" "&$G248&" "&$H248&" "&$I248&" "&$J248&" "&$K248&" "&$O248)),"SÍ","")) | B248: 247 | C248: ES | D248: Sermón | E248: El camino de regreso al cielo | F248: Sermón | G248: Fe | I248: Cielo, infierno y alma (44); Palabras y lengua (hablar bien) (32); La Biblia y su autoridad (17); Salvación y vida eterna (15); Educación de los hijos y familia (13); Gratitud y acción de gracias (11); Familia celestial y Sion (11); Avaricia y materialismo (11) | J248: Esperanza | K248: idioma, cielo, gracias, aprender, celestial, tierra, aunque, reino, hablar, lluvia, camino, cielos | L248: 35:07 | M248: 23 nov 2018 | N248: 27.108 | O248: Cristo Ahnsahnghong y Dios Madre nos enseñaron el lenguaje celestial lleno de graciaAsí como practicamos el idioma de un país antes de viajar, debemos ser capaces de hablar el idioma celestial siempre... | P248: https://watvmedia.org/es/media/the-way-back-to-heaven | Q248: https://youtu.be/TAqnj_F3dGM
A249: =IF('Buscar · Search'!$B$1="","",IF(ISNUMBER(SEARCH('Buscar · Search'!$B$1,$E249&" "&$F249&" "&$G249&" "&$H249&" "&$I249&" "&$J249&" "&$K249&" "&$O249)),"SÍ","")) | B249: 248 | C249: ES | D249: Sermón | E249: Buscando a la Madre celestial | F249: Sermón | G249: Padre/Madre, Fe, Verdad | H249: Mother | I249: La Biblia y su autoridad (74); Amor y palabra de Dios Madre (65); Educación de los hijos y familia (31); Padre celestial (Cristo Ahnsahnghong) (24); Espíritu Santo y la Esposa (16); Salvación y vida eterna (13); Avaricia y materialismo (13); Cristo Ahnsahnghong y las profecías (11) | J249: Madre, Salvación, Predicación | K249: agua, celestial, jerusalen, trono, apocalipsis, humanidad, encontrar, esposa, espiritu, mundo, fuente, jehova | L249: 30:33 | M249: 3 may 2023 | N249: 26.933 | O249: La gran profecía del libro de Apocalipsis otorgada por Dios a la humanidad.En el libro de Apocalipsis, Dios dejó una profecía para todala humanidad que sufre de hambre espiritual por oír las palabras ... | P249: https://watvmedia.org/es/media/finding-heavenly-mother | Q249: https://youtu.be/j1yx4j7Qo1c
A250: =IF('Buscar · Search'!$B$1="","",IF(ISNUMBER(SEARCH('Buscar · Search'!$B$1,$E250&" "&$F250&" "&$G250&" "&$H250&" "&$I250&" "&$J250&" "&$K250&" "&$O250)),"SÍ","")) | B250: 249 | C250: ES | D250: Sermón | E250: El camino al cielo I | F250: Sermón | G250: Padre/Madre, Carácter | I250: La Biblia y su autoridad (41); Cielo, infierno y alma (23); Padre celestial (Cristo Ahnsahnghong) (17); Avaricia y materialismo (16); Pruebas y tribulación (15); Amor y palabra de Dios Madre (15); Espíritu Santo y la Esposa (14); Educación de los hijos y familia (14) | J250: Padre, Madre, Obediencia | K250: camino, direccion, cielo, mundo, biblia, espiritu, cielos, tierra, prueba, esposa, situacion, brujula | L250: 27:45 | M250: 20 ago 2021 | N250: 26.896 | O250: ¿Cuál es la brújula espiritual que muestra a la humanidad el camino al cielo?Así como las personas que se pierden en el vasto mar o en la montaña necesitan una brújula, lo que desempeña el papel de un... | P250: https://watvmedia.org/es/media/the-way-to-heaven-i | Q250: https://youtu.be/WnT1YdTY43Y
A251: =IF('Buscar · Search'!$B$1="","",IF(ISNUMBER(SEARCH('Buscar · Search'!$B$1,$E251&" "&$F251&" "&$G251&" "&$H251&" "&$I251&" "&$J251&" "&$K251&" "&$O251)),"SÍ","")) | B251: 250 | C251: ES | D251: Sermón | E251: El aceite de la fe | F251: Sermón | G251: Fe, Carácter | I251: Fe y confianza en Dios (86); Avaricia y materialismo (25); Evangelización y predicación (15); Educación de los hijos y familia (11); La Biblia y su autoridad (8); Familia celestial y Sion (6); Arrepentimiento (6); Obediencia (4) | J251: Fe, Predicación, Obediencia | K251: mundo, aceite, tierra, ciudad, jerico, jonas, aunque, externo, ambiente, realidad, josue, cuerpo | L251: 31:42 | M251: 31 ago 2017 | N251: 26.775 | O251: Cuando el mundo interior de la fe cambia, el ambiente externo también cambia graciosamenteAsí como Josué y Caleb conquistaron la ciudad de Jericó y Jonás guio a todos los ninivitas al arrepentimiento,... | P251: https://watvmedia.org/es/media/the-oil-of-faith | Q251: https://youtu.be/42um6gZL3b8
A252: =IF('Buscar · Search'!$B$1="","",IF(ISNUMBER(SEARCH('Buscar · Search'!$B$1,$E252&" "&$F252&" "&$G252&" "&$H252&" "&$I252&" "&$J252&" "&$K252&" "&$O252)),"SÍ","")) | B252: 251 | C252: ES | D252: Sermón | E252: La familia celestial y la piedad filial espiritual | F252: Sermón | G252: Padre/Madre | I252: Educación de los hijos y familia (81); Padre celestial (Cristo Ahnsahnghong) (41); La Biblia y su autoridad (37); Amor y palabra de Dios Madre (33); Familia celestial y Sion (14); Arrepentimiento (12); Fe y confianza en Dios (10); Pruebas y tribulación (8) | J252: Dios Elohim | K252: padres, jesus, filial, esto, celestial, piedad, celestiales, hacia, familia, deber, biblia, siempre | L252: 31:46 | M252: 28 mar 2021 | N252: 26.773 | O252: En el mundo espiritual, están nuestros padres a quienes debemos honrarEl primer mandamiento es: “Ama a Dios con todo tu corazón”. Significa que debemos honrar a nuestros Padres celestiales, Cristo Ahn... | P252: https://watvmedia.org/es/media/heavenly-family-spiritual-filial-piety | Q252: https://youtu.be/rVreicI8ap8
A253: =IF('Buscar · Search'!$B$1="","",IF(ISNUMBER(SEARCH('Buscar · Search'!$B$1,$E253&" "&$F253&" "&$G253&" "&$H253&" "&$I253&" "&$J253&" "&$K253&" "&$O253)),"SÍ","")) | B253: 252 | C253: ES | D253: Sermón | E253: Los que obedecen a Dios | F253: Sermón | G253: Fe, Carácter | I253: Espíritu Santo y la Esposa (36); La Biblia y su autoridad (35); Obediencia (20); Educación de los hijos y familia (15); Palabras y lengua (hablar bien) (14); Arrepentimiento (13); Fe y confianza en Dios (8); Alegría y felicidad (8) | J253: Confiar en Dios, Fe, Obediencia | K253: espiritu, santo, siempre, jehova, pensamientos, tierra, embargo, esto, saul, escrito, pueblo, josue | L253: 34:24 | M253: 28 jul 2023 | N253: 26.734 | O253: ¿Por qué es importante la historia de la desobediencia del rey Saúl?Adán y Eva desobedecieron las palabras de Dios y escucharon a Satanás, lo que resultó en su expulsión del huerto del Edén. El rey Sa... | P253: https://watvmedia.org/es/media/those-who-obey-god | Q253: https://youtu.be/mGixSIjqHfs
A254: =IF('Buscar · Search'!$B$1="","",IF(ISNUMBER(SEARCH('Buscar · Search'!$B$1,$E254&" "&$F254&" "&$G254&" "&$H254&" "&$I254&" "&$J254&" "&$K254&" "&$O254)),"SÍ","")) | B254: 253 | C254: ES | D254: Sermón | E254: Peregrinos y errantes | F254: Sermón | G254: El nuevo pacto y las fiestas, Fe | I254: La Biblia y su autoridad (41); Avaricia y materialismo (33); Salvación y vida eterna (23); Educación de los hijos y familia (20); Fe y confianza en Dios (13); Cielo, infierno y alma (9); Palabras y lengua (hablar bien) (8); Esperanza y consuelo (8) | J254: Nuevo pacto, Esperanza, Fe | K254: mundo, tierra, reino, cielos, eterno, peregrinos, siempre, hogar, tiempo, libro, gloria, errantes | L254: 30:39 | M254: 19 ene 2024 | N254: 26.725 | O254: La diferencia entre los que viven como peregrinos y los que viven como errantesMediante la parábola del hombre rico y Lázaro, Jesús enseñó a la humanidad que la vida en esta tierra no es el fin. Lázar... | P254: https://watvmedia.org/es/media/traveler-and-wanderer | Q254: https://youtu.be/X8O2thB33QY
A255: =IF('Buscar · Search'!$B$1="","",IF(ISNUMBER(SEARCH('Buscar · Search'!$B$1,$E255&" "&$F255&" "&$G255&" "&$H255&" "&$I255&" "&$J255&" "&$K255&" "&$O255)),"SÍ","")) | B255: 254 | C255: ES | D255: Sermón | E255: La familia celestial y la Madre Celestial | F255: Sermón | G255: Padre/Madre | H255: Mother | I255: La Biblia y su autoridad (68); Amor y palabra de Dios Madre (52); Salvación y vida eterna (42); Padre celestial (Cristo Ahnsahnghong) (35); Educación de los hijos y familia (32); Cielo, infierno y alma (17); Avaricia y materialismo (16); Palabras y lengua (hablar bien) (12) | J255: Madre | K255: reino, tierra, cielos, biblia, creo, hombre, imagen, cielo, mundo, traves, esto, existe | L255: 33:00 | M255: 28 oct 2022 | N255: 26.513 | O255: Dios creó todas las cosas con su voluntad. ¿Cuál es la voluntad de Dios en la ley genética de la vida?La razón por la que Dios creó a todos los seres vivos de esta tierra para que recibieran la vida a... | P255: https://watvmedia.org/es/media/heavenly-family-heavenly-mother | Q255: https://youtu.be/7rWj3ejDtpo
A256: =IF('Buscar · Search'!$B$1="","",IF(ISNUMBER(SEARCH('Buscar · Search'!$B$1,$E256&" "&$F256&" "&$G256&" "&$H256&" "&$I256&" "&$J256&" "&$K256&" "&$O256)),"SÍ","")) | B256: 255 | C256: ES | D256: Sermón | E256: Un gran acertijo | F256: Sermón | G256: Verdad | I256: La Biblia y su autoridad (65); Salvación y vida eterna (37); Pascua (19); Arrepentimiento (14); Educación de los hijos y familia (11); Padre celestial (Cristo Ahnsahnghong) (10); Palabras y lengua (hablar bien) (9); Cielo, infierno y alma (6) | J256: Salvación | K256: arbol, jesus, eterna, carne, sangre, respuesta, tierra, pascua, camino, acertijos, pedro, vino | L256: 35:33 | M256: 20 ene 2021 | N256: 26.486 | O256: El misterio de la Biblia: “¿Quién decís que soy yo?”Dios dio a la humanidad un gran acertijo sobre la salvación de nuestras almasy el perdón de pecados. Él concederá la bendicióndel reino de los cielo... | P256: https://watvmedia.org/es/media/a-great-riddle | Q256: https://youtu.be/gGSKFKna0zU
A257: =IF('Buscar · Search'!$B$1="","",IF(ISNUMBER(SEARCH('Buscar · Search'!$B$1,$E257&" "&$F257&" "&$G257&" "&$H257&" "&$I257&" "&$J257&" "&$K257&" "&$O257)),"SÍ","")) | B257: 256 | C257: ES | D257: Sermón | E257: ¿Por qué dudaste? | F257: Sermón | G257: Fe, Verdad | I257: Cielo, infierno y alma (72); La Biblia y su autoridad (22); Avaricia y materialismo (13); Fe y confianza en Dios (9); Palabras y lengua (hablar bien) (8); Salvación y vida eterna (7); Padre celestial (Cristo Ahnsahnghong) (6); Enfermedad y sanidad (6) | J257: Biblia, Fe | K257: infierno, cielo, tierra, existen, creen, existe, mundo, agua, esto, fuego, existencia, biblia | L257: 21:07 | M257: 18 nov 2021 | N257: 26.343 | O257: ¿El cielo y el infierno no existen porque son invisibles?A través del testimonio de Job escrito hace 3500 años, Dio probó mediante la ciencia que la Biblia es verdadera y nos enseñó a creer en la exis... | P257: https://watvmedia.org/es/media/why-did-you-doubt | Q257: https://youtu.be/LsQrREEA1po
A258: =IF('Buscar · Search'!$B$1="","",IF(ISNUMBER(SEARCH('Buscar · Search'!$B$1,$E258&" "&$F258&" "&$G258&" "&$H258&" "&$I258&" "&$J258&" "&$K258&" "&$O258)),"SÍ","")) | B258: 257 | C258: ES | D258: Sermón | E258: La Fiesta de las Trompetas y el arrepentimiento | F258: Sermón | G258: El nuevo pacto y las fiestas, Fe | I258: Arrepentimiento (85); La Biblia y su autoridad (22); Educación de los hijos y familia (13); Padre celestial (Cristo Ahnsahnghong) (10); Salvación y vida eterna (7); Fiestas solemnes de Dios (7); Cielo, infierno y alma (6); Fe y confianza en Dios (5) | J258: Fiesta de las Trompetas, Arrepentimiento, Predicación | K258: arrepentimiento, pecado, jonas, antes, ninive, despues, jesus, pedro, esclavos, fiesta, trompetas, biblia | L258: 22:26 | M258: 4 oct 2019 | N258: 26.127 | O258: La Fiesta de las Trompetas es una fiesta que insta al arrepentimiento tocando trompetas diez días antes del Día de Expiación.La vida de arrepentimiento, una vida verdaderamente dignaLa vida antes del ... | P258: https://watvmedia.org/es/media/the-feast-of-trumpets-and-repentance | Q258: https://youtu.be/qBLAOLQ-AWs
A259: =IF('Buscar · Search'!$B$1="","",IF(ISNUMBER(SEARCH('Buscar · Search'!$B$1,$E259&" "&$F259&" "&$G259&" "&$H259&" "&$I259&" "&$J259&" "&$K259&" "&$O259)),"SÍ","")) | B259: 258 | C259: ES | D259: Sermón | E259: La verdad del árbol de la vida y Cristo Ahnsahnghong | F259: Sermón | G259: Padre/Madre, El nuevo pacto y las fiestas | I259: La Biblia y su autoridad (47); Pascua (40); Salvación y vida eterna (35); Arrepentimiento (14); Avaricia y materialismo (13); Padre celestial (Cristo Ahnsahnghong) (10); Educación de los hijos y familia (10); El nuevo pacto (9) | J259: Padre, Pascua | K259: arbol, pascua, jesus, vino, comer, eterna, tierra, sangre, carne, ciencia, biblia, camino | L259: 33:02 | M259: 24 mar 2022 | N259: 25.981 | O259: Cristo Ahnsahnghong nos trajo el árbol de la vida, Él es nuestro DiosLos miembros de la Iglesia de Dios creen que Cristo Ahnsahnghong es Cristo que ha venido por segunda vez porque es el único que ha ... | P259: https://watvmedia.org/es/media/the-truth-of-the-tree-of-life--christ-ahnsahnghong | Q259: https://youtu.be/jTxkIvShRbU
A260: =IF('Buscar · Search'!$B$1="","",IF(ISNUMBER(SEARCH('Buscar · Search'!$B$1,$E260&" "&$F260&" "&$G260&" "&$H260&" "&$I260&" "&$J260&" "&$K260&" "&$O260)),"SÍ","")) | B260: 259 | C260: ES | D260: Sermón | E260: El mandamiento del Día de Reposo y el culto dominical | F260: Sermón | G260: El nuevo pacto y las fiestas, Verdad | I260: La Biblia y su autoridad (70); Día de Reposo (sábado) (57); Cielo, infierno y alma (22); Asistencia al culto y adoración (20); Salvación y vida eterna (19); Palabras y lengua (hablar bien) (16); Padre celestial (Cristo Ahnsahnghong) (15); Juicio y segunda venida (13) | J260: Día de Reposo, Mandamientos, Discernimiento de la falsedad | K260: reposo, voluntad, septimo, culto, mandamientos, biblia, domingo, escrito, cielo, dominical, guardan, jesus | L260: 30:44 | M260: 24 sept 2021 | N260: 25.961 | O260: Entre el culto dominical y el Día de Reposo (sábado), ¿cuál es la obra que puede llevarnos al cielo?Así como el juez decide si el demandante y el demandado tienen razón o están equivocados en un proce... | P260: https://watvmedia.org/es/media/the-sabbath-day-commandment--sunday-worship | Q260: https://youtu.be/lxpdmRU4LoE
A261: =IF('Buscar · Search'!$B$1="","",IF(ISNUMBER(SEARCH('Buscar · Search'!$B$1,$E261&" "&$F261&" "&$G261&" "&$H261&" "&$I261&" "&$J261&" "&$K261&" "&$O261)),"SÍ","")) | B261: 260 | C261: ES | D261: Sermón | E261: La Madre celestial, el refugio más seguro | F261: Sermón | G261: Padre/Madre, Verdad | I261: La Biblia y su autoridad (49); Amor y palabra de Dios Madre (31); Familia celestial y Sion (18); Avaricia y materialismo (15); Educación de los hijos y familia (13); Padre celestial (Cristo Ahnsahnghong) (9); Salvación y vida eterna (8); Palabras y lengua (hablar bien) (7) | J261: Madre, Sion, Salvación | K261: daniel, sueno, seguro, sion, mundo, lugar, saber, refugio, tierra, escrito, celestial, jehova | L261: 26:54 | M261: 7 nov 2024 | N261: 25.860 | O261: Por qué Sion es el único refugio seguro en la tierra donde abundan los desastresLa Biblia describe proféticamente esta época como una época de gran crisis.Mientras las guerras se desatan entre las nac... | P261: https://watvmedia.org/es/media/heavenly-mother-the-safest-refuge | Q261: https://youtu.be/L9AAxfL_eE4
A262: =IF('Buscar · Search'!$B$1="","",IF(ISNUMBER(SEARCH('Buscar · Search'!$B$1,$E262&" "&$F262&" "&$G262&" "&$H262&" "&$I262&" "&$J262&" "&$K262&" "&$O262)),"SÍ","")) | B262: 261 | C262: ES | D262: Sermón | E262: Las cosas del mundo se hacen según la palabra de Dios | F262: Sermón | G262: El nuevo pacto y las fiestas, Carácter | I262: La Biblia y su autoridad (50); Cielo, infierno y alma (19); Avaricia y materialismo (13); Salvación y vida eterna (5); Educación de los hijos y familia (5); Familia celestial y Sion (4); Pascua (3); Palabras y lengua (hablar bien) (3) | J262: Pascua, Obediencia | K262: tierra, cielo, nabucodonosor, reino, daniel, hombres, interpretacion, jehova, mundo, sueno, belsasar, esto | L262: 30:47 | M262: 18 ene 2021 | N262: 25.745 | O262: Las cosas de este mundo son operadas según la voluntad de Dios Padre y Dios MadreSolo si la gente sigue las palabras de Dios,puede escapar de los desastres y llegar a la salvación.Mediante la historia... | P262: https://watvmedia.org/es/media/things-of-the-world-are-done-according-to-gods-word | Q262: https://youtu.be/bkHkJo3ujVY
A263: =IF('Buscar · Search'!$B$1="","",IF(ISNUMBER(SEARCH('Buscar · Search'!$B$1,$E263&" "&$F263&" "&$G263&" "&$H263&" "&$I263&" "&$J263&" "&$K263&" "&$O263)),"SÍ","")) | B263: 262 | C263: ES | D263: Sermón | E263: La verdad que nos liberó del pecado | F263: Sermón | G263: El nuevo pacto y las fiestas, Verdad | I263: Arrepentimiento (51); La Biblia y su autoridad (35); Padre celestial (Cristo Ahnsahnghong) (23); Educación de los hijos y familia (20); El nuevo pacto (15); Amor y palabra de Dios Madre (15); Servicio y sacrificio (11); Salvación y vida eterna (11) | J263: Nuevo pacto, Salvación | K263: pecado, muerte, camino, pacto, sangre, liberacion, carne, esto, tierra, pecados, espiritu, nunca | L263: 29:39 | M263: 1 oct 2020 | N263: 25.735 | O263: El perdón de pecados y la bendición de la salvación dada mediante el sacrificio de DiosAsí como muchos activistas de la independencia finalmente lograron la liberación de Corea, gracias al gran amor d... | P263: https://watvmedia.org/es/media/the-truth-that-set-us-free-from-sin | Q263: https://youtu.be/m6pHPGhkm-U
A264: =IF('Buscar · Search'!$B$1="","",IF(ISNUMBER(SEARCH('Buscar · Search'!$B$1,$E264&" "&$F264&" "&$G264&" "&$H264&" "&$I264&" "&$J264&" "&$K264&" "&$O264)),"SÍ","")) | B264: 263 | C264: ES | D264: Sermón | E264: La prueba del arrepentimiento | F264: Sermón | G264: Fe | I264: Arrepentimiento (101); Evangelización y predicación (48); La Biblia y su autoridad (29); Padre celestial (Cristo Ahnsahnghong) (28); Cielo, infierno y alma (25); Educación de los hijos y familia (23); Salvación y vida eterna (13); Pruebas y tribulación (13) | J264: Arrepentimiento, Predicación | K264: arrepentimiento, jesus, cielo, predicar, arrepentido, tierra, predicacion, prueba, reino, cielos, estaba, evangelio | L264: 32:25 | M264: 29 mar 2021 | N264: 25.647 | O264: El mandamiento de Dios visibiliza nuestra fe que es invisible. La prueba del arrepentimiento, que es invisible, es predicar. Dios comprueba si creemos o no en Élviendo si guardamos o no sus mandamient... | P264: https://watvmedia.org/es/media/proof-of-repentance | Q264: https://youtu.be/mD5bSy_lPVE
...

Sheet Temas · Topics
A1: Idioma | B1: Tema / Topic | C1: Nº | D1: Título / Title | E1: Tipo | F1: Duración | G1: Fecha | H1: Menciones | I1: Enlace / Link
A2: ES | B2: Alegría y felicidad | C2: 1 | D2: El secreto de la felicidad y el reino de los cielos | E2: Sermón | F2: 32:35 | G2: 19 ago 2022 | H2: 40 | I2: https://watvmedia.org/es/media/the-secret-to-happiness-the-kingdom-of-heaven
A3: ES | B3: Alegría y felicidad | C3: 2 | D3: Dios prueba los corazones | E3: Sermón | F3: 30:08 | G3: 11 feb 2022 | H3: 22 | I3: https://watvmedia.org/es/media/god-tests-the-heart
A4: ES | B4: Alegría y felicidad | C4: 3 | D4: La ley de Dios y el fruto de los pensamientos | E4: Sermón | F4: 30:53 | G4: 7 mar 2025 | H4: 20 | I4: https://watvmedia.org/es/media/the-results-of-gods-law-and-thoughts
A5: ES | B5: Alegría y felicidad | C5: 4 | D5: Separados de Dios, no podemos vivir | E5: Sermón | F5: 37:01 | G5: 22 dic 2023 | H5: 19 | I5: https://watvmedia.org/es/media/you-cant-live-without-god
A6: ES | B6: Alegría y felicidad | C6: 5 | D6: Para a la postre hacerte bien | E6: Sermón | F6: 34:02 | G6: 3 jul 2026 | H6: 17 | I6: https://watvmedia.org/es/media/god-wants-to-bless-him-in-the-end
A7: ES | B7: Alegría y felicidad | C7: 6 | D7: La Fiesta de los Panes sin Levadura y la evangelización mundial | E7: Sermón | F7: 29:28 | G7: 15 abr 2022 | H7: 16 | I7: https://watvmedia.org/es/media/the-feast-of-unleavened-bread-and-world-evangelism
A8: ES | B8: Alegría y felicidad | C8: 7 | D8: Anhelo por la eternidad | E8: Sermón | F8: 31:14 | G8: 23 mar 2024 | H8: 15 | I8: https://watvmedia.org/es/media/a-heart-that-longs-for-eternity
A9: ES | B9: Alegría y felicidad | C9: 8 | D9: Estad siempre gozosos | E9: Mensual | F9: 08:06 | G9: 3 jul 2025 | H9: 13 | I9: https://watvmedia.org/es/media/always-be-happy
A10: ES | B10: Alegría y felicidad | C10: 9 | D10: Los placeres del pecado y los placeres del cielo | E10: Sermón | F10: 31:55 | G10: 9 jul 2026 | H10: 13 | I10: https://watvmedia.org/es/media/the-pleasures-of-sin-and-the-pleasures-of-heaven
A11: ES | B11: Alegría y felicidad | C11: 10 | D11: ¿Quién soy? | E11: Sermón | F11: 27:31 | G11: 4 ago 2023 | H11: 12 | I11: https://watvmedia.org/es/media/who-am-i
A12: ES | B12: Alegría y felicidad | C12: 11 | D12: Dios Madre, la Arquitecta de la vida | E12: Sermón | F12: 20:25 | G12: 13 nov 2023 | H12: 11 | I12: https://watvmedia.org/es/media/god-the-mother-the-architect-of-life
A13: ES | B13: Alegría y felicidad | C13: 12 | D13: El corazón de la Madre y Sion | E13: Sermón | F13: 30:32 | G13: 23 ene 2018 | H13: 10 | I13: https://watvmedia.org/es/media/mothers-heart-zion
... A5845: ES | B5845: Unidad y armonía | C5845: 13 | D5845: Seamos uno | E5845: Resumen | F5845: 04:10 | G5845: 19 feb 2026 | H5845: 3 | I5845: https://watvmedia.org/es/media/lets-become-one
A5846: EN | B5846: Anger and temper | C5846: 1 | D5846: The Way Back to Heaven | E5846: Sermón | F5846: 35:07 | H5846: 26 | I5846: https://watvmedia.org/en/media/the-way-back-to-heaven
A5847: EN | B5847: Anger and temper | C5847: 2 | D5847: Words that Bring Blessings | E5847: Sermón | F5847: 31:21 | H5847: 22 | I5847: https://watvmedia.org/en/media/words-that-bring-blessings
A5848: EN | B5848: Anger and temper | C5848: 3 | D5848: Day of Judgment & Day of Salvation | E5848: Sermón | F5848: 30:40 | H5848: 20 | I5848: https://watvmedia.org/en/media/day-of-judgment-day-of-salvation
A5849: EN | B5849: Anger and temper | C5849: 4 | D5849: Words Leading to Blessings | E5849: Sermón | F5849: 29:10 | H5849: 19 | I5849: https://watvmedia.org/en/media/words-that-lead-to-blessings
A5850: EN | B5850: Anger and temper | C5850: 5 | D5850: Bad Habits & Good Habits | E5850: Sermón | F5850: 37:11 | H5850: 15 | I5850: https://watvmedia.org/en/media/bad-habits-good-habits
A5851: EN | B5851: Anger and temper | C5851: 6 | D5851: Do Not Put God to the Test | E5851: Sermón | F5851: 32:04 | H5851: 14 | I5851: https://watvmedia.org/en/media/do-not-put-god-to-the-test
A5852: EN | B5852: Anger and temper | C5852: 7 | D5852: Heavenly Language | E5852: Sermón | F5852: 28:54 | H5852: 14 | I5852: https://watvmedia.org/en/media/language-of-heaven
A5853: EN | B5853: Anger and temper | C5853: 8 | D5853: The Commandment of Love | E5853: Sermón | F5853: 29:13 | H5853: 14 | I5853: https://watvmedia.org/en/media/the-commandment-of-love
A5854: EN | B5854: Anger and temper | C5854: 9 | D5854: God the Savior of Our Life | E5854: Sermón | F5854: 36:13 | H5854: 13 | I5854: https://watvmedia.org/en/media/god-the-savior-of-our-life
A5855: EN | B5855: Anger and temper | C5855: 10 | D5855: Longing for Eternity | E5855: Sermón | F5855: 31:14 | H5855: 13 | I5855: https://watvmedia.org/en/media/a-heart-that-longs-for-eternity
A5856: EN | B5856: Anger and temper | C5856: 11 | D5856: The Festival of Trumpets & the Trumpet of Repentance | E5856: Sermón | F5856: 29:51 | H5856: 12 | I5856: https://watvmedia.org/en/media/the-feast-of-trumpets-and-the-trumpet-of-repentance
A5857: EN | B5857: Anger and temper | C5857: 12 | D5857: The Focus of Life & Gratitude | E5857: Sermón | F5857: 31:55 | H5857: 11 | I5857: https://watvmedia.org/en/media/the-focus-of-life--gratitude
... A12253: EN | B12253: Worship and service attendance | C12253: 98 | D12253: What Day of the Week Is the Sabbath Day of the New Covenant? | E12253: Resumen | F12253: 08:31 | H12253: 3 | I12253: https://watvmedia.org/en/media/what-day-of-the-week-is-the-sabbath-day-of-the-new-covenant

Sheet Mensual · Monthly
A1: Idioma | B1: Título / Title | C1: Duración | D1: Fecha | E1: Temas / Topics | F1: Enlace / Link
A2: ES | B2: Deben nacer de nuevo para entrar en el Reino de los Cielos | C2: 05:24 | D2: 14 dic 2023 | E2: Amor y amor fraternal; Cielo, infierno y alma; Educación de los hijos y familia; Salvación y vida eterna; Evangelización y predicación; Avaricia y materialismo; Arrepentimiento | F2: https://watvmedia.org/es/media/be-born-again
A3: ES | B3: Nuestra patria es el cielo: somos extranjeros sobre la tierra | C3: 06:49 | D3: 5 mar 2025 | E3: Cielo, infierno y alma; Salvación y vida eterna; Educación de los hijos y familia; Arrepentimiento; Padre celestial (Cristo Ahnsahnghong); Avaricia y materialismo; Familia celestial y Sion; Enfermedad y sanidad | F3: https://watvmedia.org/es/media/our-home-is-heaven-we-are-strangers-in-this-world
A4: ES | B4: El lino fino de Dios | C4: 08:02 | D4: 30 abr 2025 | E4: Amor y amor fraternal; Salvación y vida eterna; Avaricia y materialismo; Palabras y lengua (hablar bien); Pascua; La Biblia y su autoridad; Ira y enojo (control del temperamento); Educación de los hijos y familia | F4: https://watvmedia.org/es/media/gods-linen
A5: ES | B5: Una fe que practica la unidad | C5: 07:10 | D5: 18 oct 2024 | E5: Cielo, infierno y alma; Unidad y armonía; Salvación y vida eterna; Perdón y reconciliación; Pruebas y tribulación; Evangelización y predicación; Enfermedad y sanidad | F5: https://watvmedia.org/es/media/united-faith
A6: ES | B6: Edifiquemos a los demás con palabras amables y hermosas | C6: 07:34 | D6: 17 jun 2025 | E6: Palabras y lengua (hablar bien); Salvación y vida eterna; Educación de los hijos y familia; Ira y enojo (control del temperamento); Fe y confianza en Dios; Alegría y felicidad; Humildad y orgullo | F6: https://watvmedia.org/es/media/let-us-bestow-grace-with-good-and-beautiful-words
A7: ES | B7: ¿Haciendo qué cosa heredaré la vida eterna? | C7: 06:53 | D7: 22 oct 2024 | E7: Amor y amor fraternal; Cielo, infierno y alma; Salvación y vida eterna; Padre celestial (Cristo Ahnsahnghong); Evangelización y predicación; Pascua; Palabras y lengua (hablar bien) | F7: https://watvmedia.org/es/media/how-eternal-life
A8: ES | B8: Las cosas buenas y las cosas malas | C8: 06:04 | D8: 24 ene 2025 | E8: Cielo, infierno y alma; Educación de los hijos y familia; Perdón y reconciliación; Palabras y lengua (hablar bien); Amor y amor fraternal; Arrepentimiento; Salvación y vida eterna | F8: https://watvmedia.org/es/media/the-good-and-the-bad
A9: ES | B9: Conformarse a las sanas palabras y a la doctrina que es conforme a la piedad | C9: 07:05 | D9: 22 nov 2024 | E9: Educación de los hijos y familia; Cielo, infierno y alma; Salvación y vida eterna; La Biblia y su autoridad; Palabras y lengua (hablar bien); Amor y amor fraternal | F9: https://watvmedia.org/es/media/focus-on-reverence-and-the-word
A10: ES | B10: Todas las naciones correrán a Sion por el camino de la vida | C10: 06:58 | D10: 5 dic 2024 | E10: Salvación y vida eterna; Familia celestial y Sion; Pascua; Fiestas solemnes de Dios; La Biblia y su autoridad; Evangelización y predicación; El nuevo pacto | F10: https://watvmedia.org/es/media/all-nations-find-their-way-to-zion
A11: ES | B11: Según las palabras de la profecía | C11: 06:23 | D11: 22 nov 2024 | E11: Salvación y vida eterna; Cristo Ahnsahnghong y las profecías; La Biblia y su autoridad; Palabras y lengua (hablar bien); Pascua; Cielo, infierno y alma; Arrepentimiento; Familia celestial y Sion | F11: https://watvmedia.org/es/media/words-of-prophecy
A12: ES | B12: Mirad, velad y orad | C12: 05:51 | D12: 24 ene 2025 | E12: Salvación y vida eterna; Padre celestial (Cristo Ahnsahnghong); Educación de los hijos y familia; Pascua; Cristo Ahnsahnghong y las profecías | F12: https://watvmedia.org/es/media/be-careful-stay-awake
... A28: ES | B28: La felicidad de los ciudadanos celestiales | C28: 07:15 | D28: 17 sept 2026 | E28: Educación de los hijos y familia; Amor y amor fraternal; Salvación y vida eterna; Alegría y felicidad; Cielo, infierno y alma; Padre celestial (Cristo Ahnsahnghong); Evangelización y predicación; Espíritu Santo y la Esposa | F28: https://watvmedia.org/es/media/heavenly-citizens-happiness
A29: EN | B29: You Will Reap What You Sow | C29: 06:25 | E29: Love and brotherly love; Heavenly family and Zion; Evangelism and preaching; Words and the tongue; Passover; Heaven, hell and the soul; Anger and temper | F29: https://watvmedia.org/en/media/you-will-reap-what-you-sow
A30: EN | B30: The Word of God Will Stand Forever | C30: 06:52 | E30: Heaven, hell and the soul; Salvation and eternal life; Joy and happiness; Words and the tongue; Hope and comfort; Trials and suffering; Faith and trust in God | F30: https://watvmedia.org/en/media/word-of-god-will-stand-forever
A31: EN | B31: The Happiness of Heavenly Citizens | C31: 07:15 | E31: Love and brotherly love; Heaven, hell and the soul; Children and family; Salvation and eternal life; Joy and happiness; Evangelism and preaching; Words and the tongue; Holy Spirit and the Bride | F31: https://watvmedia.org/en/media/heavenly-citizens-happiness
A32: EN | B32: Achieve Perfect Love | C32: 06:56 | E32: Heaven, hell and the soul; Love and brotherly love; Salvation and eternal life; Prayer; Evangelism and preaching; Children and family; Service and sacrifice; Trials and suffering | F32: https://watvmedia.org/en/media/be-perfect-in-love
A33: EN | B33: Our Citizenship Is in Heaven | C33: 07:36 | E33: Heaven, hell and the soul; Salvation and eternal life; Evangelism and preaching; Children and family; The Bible and its authority; Patience and self-control; Words and the tongue; The new covenant | F33: https://watvmedia.org/en/media/our-citizenship-is-in-heaven1
A34: EN | B34: Be Ready and Preach the Gospel | C34: 07:11 | E34: Evangelism and preaching; Heaven, hell and the soul; Salvation and eternal life; Heavenly family and Zion; Love and brotherly love; Children and family; Passover; Money, work and provision | F34: https://watvmedia.org/en/media/be-ready-preach-the-gospel
A35: EN | B35: The Necessity of the Holy Spirit | C35: 06:42 | E35: Holy Spirit and the Bride; Salvation and eternal life; Heaven, hell and the soul; Evangelism and preaching; Words and the tongue; Obedience; Faith and trust in God | F35: https://watvmedia.org/en/media/the-necessity-of-the-holy-spirit-1
A36: EN | B36: The Fruit of Love Brought Forth Through Humility | C36: 07:38 | E36: Love and brotherly love; Humility and pride; Words and the tongue; Heaven, hell and the soul; Heavenly family and Zion; Children and family; Salvation and eternal life; Money, work and provision | F36: https://watvmedia.org/en/media/channel-video-688589
A37: EN | B37: Autumn Trees Bearing Fruit | C37: 07:40 | E37: Words and the tongue; Heavenly family and Zion; Heaven, hell and the soul; Evangelism and preaching; Salvation and eternal life; The Bible and its authority; Prophecy and Christ Ahnsahnghong; Money, work and provision | F37: https://watvmedia.org/en/media/autumn-tree-bearing-fruits
A38: EN | B38: Live Peacefully With Each Other in Love | C38: 07:38 | E38: Heaven, hell and the soul; Evangelism and preaching; Heavenly family and Zion; Unity and harmony; Salvation and eternal life; Love and brotherly love; Humility and pride; Words and the tongue | F38: https://watvmedia.org/en/media/channel-video-751171
A39: EN | B39: The Faith That Reveres God | C39: 08:52 | E39: Words and the tongue; Salvation and eternal life; Heaven, hell and the soul; Faith and trust in God; Heavenly family and Zion | F39: https://watvmedia.org/en/media/faith-that-fears-god
A40: EN | B40: Rejoice Always | C40: 08:05 | E40: Joy and happiness; Salvation and eternal life; Heaven, hell and the soul; Evangelism and preaching; Holy Spirit and the Bride; Prayer; Heavenly family and Zion; Children and family | F40: https://watvmedia.org/en/media/always-be-happy
... A56: EN | B56: You Must Be Born Again to Enter the Kingdom of Heaven | C56: 05:26 | E56: Love and brotherly love; Heaven, hell and the soul; Children and family; Salvation and eternal life; Evangelism and preaching; Words and the tongue; Trials and suffering; Joy and happiness | F56: https://watvmedia.org/en/media/be-born-again

Sheet Etiquetas · Tags
A1: Idioma | B1: Etiqueta / Tag | C1: Nº | D1: Títulos / Titles
A2: ES | B2: Fe | C2: 184 | D2: Superemos la tentación y obtengamos el reino de los cielos | El que cree y el que no cree | La fe cambia al mundo | La petición del Padre: “Vivan para la misión” | La vida y la muerte, y el camino de la vida eterna | Dios es la respuesta | No tentarás a Dios | En Él que me fortalece | Nunca digan no | El camino celestial que recorremos por la fe | Las Escrituras dicen que es necesario que así se haga | El valor del cielo y el valor del mundo | En verdad, qué benditos | Esfuérzate y sé valiente | Este es el problema | Los que no conocen el valor no tienen derecho a poseerlo | La tentación y la victoria | El mundo invisible y la verdadera fe | Hagan como la Biblia instruye | La fe en Dios | Retribuyamos la gracia de Dios | La familia celestial y jactarse de Dios | La salvación concedida a los que perseveren hasta el fin | Sé celoso, porque el reino de los cielos se ha acercado | Dios puede hacerlo todo
A3: ES | B3: Nuevo pacto | C3: 167 | D3: La verdad y la falsedad | La Pascua y el Orden de Melquisedec | Dios, la fuente de la sabiduría | El Salvador de cada época y el nombre nuevo | La bendición de Dios y el Día de Reposo | El rey David y el nuevo pacto | El día del juicio | La sal y la luz del mundo La vida de un cristiano | Cristo Ahnsahnghong y las profecías | La ciudad de refugio y la tierra | La iglesia establecida por la raíz de David y la verdad del nuevo pacto | La tierra, la ciudad de refugio, y el sistema del nuevo pacto | El rey David y Cristo Ahnsahnghong | La prueba de que somos hijos de Dios | El Espíritu y la Esposa nos llaman | Cuando Israel era fuerte y cuando Israel era débil | El maná escondido y el nombre nuevo | ¿Qué es lo más valioso en el cielo? | Enseñad lo que os he mandado | Una vida sin respuestas | Una convocación repentina | La verdad del árbol de la vida | Los que pueden oír correctamente la voz de Dios | Las características del cristianismo auténtico y de la herejía | La comida dada por Dios
A4: ES | B4: Salvación | C4: 133 | D4: Las profecías de los profetas y los pensamientos de la gente del mundo | El que cree y el que no cree | Dios, la fuente de la sabiduría | Desechemos la arrogancia y seamos humildes | El cielo o el infierno según nuestras obras | ¡Qué hermoso será! | Nuestra Madre Celestial II | Cuando la vida no tiene sentido | El rey David y Cristo Ahnsahnghong | La prueba de que somos hijos de Dios | Cuando Israel era fuerte y cuando Israel era débil | Una vida sin respuestas | Elecciones de los que conocen el valor | Una convocación repentina | El mundo invisible y la verdadera fe | Hagan como la Biblia instruye | Juicio, cielo o infierno | La voz de la Madre celestial | Planes para el cielo y planes para la jubilación | La vida como el rocío sobre la hierba | Alumbren la gloria de Jerusalén al mundo entero | El significado del Día de Expiación | El Padre Ahnsahnghong es Dios, Cristo que vino por segunda vez VI | La preparación de Dios y nuestra preparación | La Pascua por la cual podemos volver a Dios
A5: ES | B5: Madre | C5: 111 | D5: La Madre Jerusalén | Búscame | Dios, la fuente de la sabiduría | La Madre Jerusalén y la vida eterna | Conozcamos a Dios | El corazón de la Madre y Sion | Nuestra Madre Celestial II | La historia de la familia de Abraham y la Madre | Discernamos entre la verdad y la falsedad | La familia celestial y la familia terrenal 2 | Los hijos de la promesa y la profecía de Abraham | La Madre Celestial Jerusalén | El corazón de los Padres celestiales | Vengan al Espíritu y la Esposa | El Espíritu y la Esposa nos llaman | Madre, gracias, la amamos | Sigan el arca del pacto | La Madre, la Fuente del Agua de la Vida | Jerusalén, el trono del juicio II | La voz de la Madre celestial | La familia celestial y la familia terrenal III | Los que pueden oír correctamente la voz de Dios | La obra de la salvación a través de la Madre | Un buen árbol lleva buenos frutos | La Madre celestial y el Lugar Santísimo
A6: ES | B6: Pascua | C6: 102 | D6: El secreto del perdón de pecados y la Pascua | La Pascua y el Orden de Melquisedec | Dios, la fuente de la sabiduría | ¡Qué hermoso será! | La educación celestial y los ojos de amor | Un desastre sin igual y la Pascua | La ciudad de refugio y la tierra | La iglesia establecida por la raíz de David y la verdad del nuevo pacto | La prueba de que somos hijos de Dios | El maná escondido y el nombre nuevo | La Pascua es la verdad que salva vidas | La Santa Comunión de la Pascua que Dios nos ordenó celebrar | La ciudad de refugio espiritual y la tierra | La verdad del árbol de la vida | La Pascua es el camino y la verdad | La comida dada por Dios | La profecía y Dios | La ley de vida, la Pascua | La invitación de Dios | La marca de Dios y la marca de la bestia | El Padre Ahnsahnghong es Dios, Cristo que vino por segunda vez VI | La Pascua que Dios nos ordenó celebrar | La Pascua por la cual podemos volver a Dios | La Pascua y la bendición de Dios | La verdad del árbol de la vida y Cristo Ahnsahnghong
A7: ES | B7: Predicación | C7: 93 | D7: Una vida valiosa | Si conocen, amarán | La petición del Padre: “Vivan para la misión” | Resolviendo los malentendidos y revelando la verdad | Nunca digan no | Dios, el Salvador de la vida | La fuente de poder que cumple la obra de la salvación de Dios | La predicación de la iglesia primitiva y la predicación en la última época | Alumbremos la luz de la gloria de Jerusalén | Planes para el cielo y planes para la jubilación | Los que se arrepienten y los que no se arrepienten | Dios puede hacerlo todo | ¿Cuántos días quedan en nuestra vida? | La última oportunidad | Levántate, resplandece II | La reacción de la humanidad ante la venida de Dios en la carne | La predicación del evangelio y la responsabilidad | No consultaron a Dios | Todo es posible en el mundo de la fe | Buscando a la Madre celestial | El aceite de la fe | La Fiesta de las Trompetas y el arrepentimiento | La prueba del arrepentimiento | Los que son dignos del reino de Dios | Servir a los demás y predicar
A8: ES | B8: Obediencia | C8: 90 | D8: Conozcamos a Dios | Los malos hábitos y los buenos hábitos | El eterno mundo angelical y el reino celestial | El camino al cielo y el camino al desierto (II) | Nunca digan no | Cuando Israel era fuerte y cuando Israel era débil | Dios, el Salvador de la vida | Ascender al cielo caminando con Dios | Quien quiera llevar la corona, debe soportar su peso | La obediencia es la fuente de la salvación | La fe en Dios | Retribuyamos la gracia de Dios | Jerusalén, el trono del juicio II | La familia celestial y jactarse de Dios | La palabra de Dios y su poder | El que obedece a Dios | El valor del pensamiento racional y el valor de seguir a Cristo | El número 1 | Los que buscan a Dios | Sus nombres serán escritos en el libro de la vida | No consultaron a Dios | El camino al cielo I | El aceite de la fe | Los que obedecen a Dios | Las cosas del mundo se hacen según la palabra de Dios
A9: ES | B9: Padre | C9: 84 | D9: El Salvador y el nombre nuevo | La parábola de la higuera y Cristo Ahnsahnghong | El Padre Ahnsahnghong es Dios, Cristo que vino por segunda vez II | Conozcamos a Dios | El Salvador de cada época y el nombre nuevo | La petición del Padre: “Vivan para la misión” | La familia celestial y la familia terrenal 2 | Cristo Ahnsahnghong y las profecías | El corazón de los Padres celestiales | Vendrá en las nubes | Vengan al Espíritu y la Esposa | El rey David y Cristo Ahnsahnghong | El Espíritu y la Esposa nos llaman | Sigan el arca del pacto | El poder de la palabra de Dios | Hagan como la Biblia instruye | La trinidad y Dios | La importancia del nombre de Dios dado en cada época | Los que pueden oír correctamente la voz de Dios | El rey David y Cristo Ahnsahnghong (II) | El nuevo pacto y Dios | La promesa y la garantía del cielo | El Señor Ahnsahnghong es Dios, Cristo que vino por segunda vez 1 | El gran misterio, el secreto de la Biblia | La trinidad
A10: ES | B10: Esperanza | C10: 71 | D10: El cielo o el infierno según nuestras obras | La fe cambia al mundo | Vivir para un momento y vivir para la eternidad | Cuando la vida no tiene sentido | Vayamos al glorioso reino de Dios | Acerca del alma (2) | Los que entrarán en el reino de Dios | El valor del cielo y el valor del mundo | Madre, gracias, la amamos | ¿Qué es lo más valioso en el cielo? | El secreto de la felicidad y el reino de los cielos | Elecciones de los que conocen el valor | La Resurrección y la transformación | ¿Cuántos días quedan en nuestra vida? | Los que emigran | El camino de regreso al cielo | Peregrinos y errantes | Vayamos al cielo, no al infierno | El camino del rey | Anhelo por la eternidad | Los obreros del nuevo pacto del Espíritu y la Esposa | Un instrumento del poder de Dios, la oración | El grito de Josué | El poder de la obediencia | Dios Madre, la Arquitecta de la vida
A11: ES | B11: Dios en la carme | C11: 56 | D11: Las profecías de los profetas y los pensamientos de la gente del mundo | El Salvador y el nombre nuevo | El Padre Ahnsahnghong es Dios, Cristo que vino por segunda vez II | Búscame | El camino de la verdad | La historia de la familia de Abraham y la Madre | Oportunidad | No tentarás a Dios | Cristo Ahnsahnghong y las profecías | Vendrá en las nubes | La Madre, la Fuente del Agua de la Vida | El poder de la palabra de Dios | La trinidad y Dios | El rey David y Cristo Ahnsahnghong (II) | La fe de la iglesia primitiva | El nuevo pacto y Dios | El Señor Ahnsahnghong es Dios, Cristo que vino por segunda vez 1 | La reacción de la humanidad ante la venida de Dios en la carne | Nuestro Dios omnipotente y omnisciente | El entendimiento que Dios nos ha dado | El Señor Ahnsahnghong es Dios, Cristo que vino por segunda vez IV | El corazón angustiado de Dios | El cristianismo tildado de herejía | El misterio de Dios | Cristo Ahnsahnghong que vino por segunda vez
A12: ES | B12: Fiestas Solemnes | C12: 53 | D12: Cuando Israel era fuerte y cuando Israel era débil | El Día de Pentecostés | El templo y las ordenanzas de Dios | Ofrezcamos culto sagrado a Dios | Dios castigará la tierra | Cristo Ahnsahnghong estableció Sion | Las fiestas solemnes y los mandamientos de Dios | Anhelo por la eternidad | La parábola de las diez vírgenes y la convicción en la verdad | La ley de Dios fue tenida por cosa extraña | Guarden el mandamiento de la Pascua | ¿Quiénes son el verdadero pueblo de Dios? | El Día de Ascensión y la esperanza de la ascensión | Un instrumento del poder de Dios, la oración | Me seréis testigos | Solo lo que proviene de Dios es auténtico | Dios Ahnsahnghong estableció a Sion | La resurrección y el cuerpo espiritual | La hermosa resurrección | La Pascua, la bendición de la vida eterna | ¿Quién recibe el Espíritu Santo de la lluvia tardía? | La Fiesta de las Primicias del Antiguo Testamento y el Día de Resurrección | La Fiesta de los Tabernáculos y la construcción del templo | Por mis pecados | La finalización del templo de Jerusalén y la Fiesta de los Tabernáculos
A13: ES | B13: Gratitud | C13: 46 | D13: Mi amado Dios | No es el mundo el que debe cambiar primero sino nosotros | Den gracias y alabanza a Dios | Respétense mutuamente | He aquí que te he dado | Palabras de esperanza para aquellos en desesperación | Este es el problema | Madre, gracias, la amamos | ¿Qué haré ahora, Señor? | Somos bienaventurados | El secreto de la felicidad y el reino de los cielos | Separados de Dios, no podemos vivir | Las palabras y la predicación | Palabras que traen bendiciones | El hábito que nos conduce a la vida eterna y la salvación | El enfoque de la vida y la gratitud | ¿A quién debemos estar más agradecidos? | ¿Es feliz? | La fe y la obediencia | El idioma del cielo y el idioma del infierno | Dios Madre, la Arquitecta de la vida | Los que viven según las profecías | Los anillos de crecimiento celestiales | La Fiesta de los Panes sin Levadura y la pasión | La devoción y el sacrificio de los Padres
... A111: EN | B111: Self-Sufficiency | C111: 1 | D111: What Is the Life of Those Who Will Be Kings
